Workbook

Sheet JULHO  2026
C1: GOVERNO DO ESTADO DA BAHIA
C2: Secretaria da Saúde do Estado da Bahia – SESAB
C3: Hospital Geral Clériston Andrade - HGCA
G4: Feira de Santana, 26 de AGOSTO de 2026.
B6: De: Contas Hospitalares
B7: Para: Diretoria Médica/ Coordenação Neurologia
B8: Relatório de pacientes que realizaram neurocirurgia no HGCA em JULHO 2026
A10: N° | B10: Nome: | C10: Data da cirurgia | D10: Número de registro | E10: Código Sigtap | F10: Descritivo | G10: Valor SP SIGITAP | H10: Profissional | J10: OBS
A11: 1 | B11: CARMELITA MARIA DE JESUS | C11: 46205 | D11: 19999507 | E11: 0408030291 | F11: ='0408030'!B42 -> artrodese toraco-lombo-sacra posterior 2 niveis | G11: ='0408030'!C42 -> 1155.78 | H11: ='por medico'!A17 -> EDUARDO VARJÃO VIEIRA | J11: OPME
E12: 0408030135 | F12: ='0408030'!B25 -> artrodese intersomatica vias posterior /postero lateral 1 nivel | G12: ='0408030'!C25 -> 611 | H12: ='por medico'!A21 -> WAGNER DE AZEVEDO HERCULANO
E13: 0408030380 | F13: ='0408030'!B51 -> disectomia cervical/lombar/lombo-sacra por via posterior (1 nivel com microscopio) | G13: ='0408030'!C51 -> 470
E14: 0403020115 | F14: ='0403020'!B23 -> tratamento cirurgico de neuropatia compressiva com ou sem microcirurgia | G14: ='0403020'!C23 -> 560
E15: 0408030542 | F15: ='0408030'!B66 -> ressecção de elemento vertebral posterior /postero-lateral /distal a C2 ( até 2 segmentos) | G15: ='0408030'!C66 -> 288
F16: TOTAL | G16: =SUM(G11:G15) -> 3084.78
A17: 2 | B17: JAILSON DE JESUS NUNES | C17: 46205 | D17: 20170007 | E17: 0408030917 | F17: ='0408030'!B104 -> artrodese cervical /cervico toráxica posterior 4 niveis | G17: ='0408030'!C104 -> 1155.78 | H17: ='por medico'!A21 -> WAGNER DE AZEVEDO HERCULANO | J17: OPME
E18: 0403010250 | F18: ='0403010'!B38 -> tratamento cirurgico de fistula liquorica raquidiana | G18: ='0403010'!C38 -> 671.94 | H18: ='por medico'!A17 -> EDUARDO VARJÃO VIEIRA
E19: 0403020115 | F19: ='0403020'!B23 -> tratamento cirurgico de neuropatia compressiva com ou sem microcirurgia | G19: ='0403020'!C23 -> 560
E20: 0408030534 | F20: ='0408030'!B65 -> ressecção de elemento vertebral posterior /postero-lateral /distal a C2 (mais de 2 segmentos) | G20: ='0408030'!C65 -> 345.6
F22: TOTAL | G22: =SUM(G17:G21) -> 2733.32
A23: 3 | B23: MOISANE DE OLIVERIA COSTA | C23: 46205 | D23: 18270306 | E23: 0403010101 | F23: ='0403010'!B22 -> derivação ventricular para peritoneo/atrio/pleura/raque | G23: ='0403010'!C22 -> 682.08 | H23: ='por medico'!A21 -> WAGNER DE AZEVEDO HERCULANO | J23: OPME
E24: 0403010365 | F24: ='0403010'!B49 -> trepanação craniana para punção ou biopsia | G24: ='0403010'!C49 -> 107.52 | H24: ='por medico'!A17 -> EDUARDO VARJÃO VIEIRA
F28: TOTAL | G28: =SUM(G23:G27) -> 789.6
A29: 4 | B29: ALBERTO CASTRO DOS SANTOS | C29: 46205 | D29: 16019804 | E29: 0403010314 | F29: ='0403010'!B44 -> Tratamento cirurgico de hematoma subdural cronico | G29: ='0403010'!C44 -> 682.08 | H29: ='por medico'!A17 -> EDUARDO VARJÃO VIEIRA | J29: OPME
E30: 0403010020 | F30: ='0403010'!B14 -> Craniotomia descompressiva | G30: ='0403010'!C14 -> 391.86 | H30: ='por medico'!A21 -> WAGNER DE AZEVEDO HERCULANO
F34: TOTAL | G34: =SUM(G29:G33) -> 1073.94
A35: 5 | B35: JOSE HENRIQUE COSTA SOUZA | C35: 46205 | D35: 20207494 | E35: 0403010241 | F35: ='0403010'!B37 -> tratamento cirurgico de fistula liquorica craniana | G35: ='0403010'!C37 -> 671.94 | H35: ='por medico'!A17 -> EDUARDO VARJÃO VIEIRA | J35: OPME
E36: 0403010284 | F36: ='0403010'!B41 -> tratamento cirurgico de hematoma intracerebral | G36: ='0403010'!C41 -> 488.99 | H36: ='por medico'!A21 -> WAGNER DE AZEVEDO HERCULANO
E37: 0403010020 | F37: ='0403010'!B14 -> Craniotomia descompressiva | G37: ='0403010'!C14 -> 391.86
F40: TOTAL | G40: =SUM(G35:G39) -> 1552.79
A41: 6 | B41: GIZELA SANTOS AMPAIO | C41: 46205 | D41: 20207510 | E41: 0403010187 | F41: ='0403010'!B30 -> revisão derivação ventricular para peritoneo/atrio/pleura/raque | G41: ='0403010'!C30 -> 572 | H41: ='por medico'!A15 -> JAQUISSON DE DEUS GUIMARÃES FILHO | J41: OPME
E42: 0403010098 | F42: ='0403010'!B21 -> derivação ventricular externa -subgaleal externa | G42: ='0403010'!C21 -> 286 | H42: ='por medico'!A21 -> WAGNER DE AZEVEDO HERCULANO
E43: 0403010365 | F43: ='0403010'!B49 -> trepanação craniana para punção ou biopsia | G43: ='0403010'!C49 -> 107.52
F46: TOTAL | G46: =SUM(G41:G45) -> 965.52
A47: 7 | B47: FIRMINA BATISTA | C47: 46206 | D47: 19937804 | E47: 0408030267 | F47: ='0408030'!B38 -> artrodese toraco-lombo-sacra posterior 1 nivel | G47: ='0408030'!C38 -> 470 | H47: ='por medico'!A21 -> WAGNER DE AZEVEDO HERCULANO
E48: 0408030542 | F48: ='0408030'!B66 -> ressecção de elemento vertebral posterior /postero-lateral /distal a C2 ( até 2 segmentos) | G48: ='0408030'!C66 -> 288 | H48: ='por medico'!A23 -> ARTUR BASTOS ROCHA
F52: TOTAL | G52: =SUM(G47:G51) -> 758
A53: 8 | B53: JUCINEIDE DOS SANTOS SILVA | C53: 46205 | D53: 14123228 | E53: 0403030099 | F53: ='0403030'!B20 -> microcirurgia de tumor medular técnica complementar | G53: ='0403030'!C20 -> 1540.56 | H53: ='por medico'!A21 -> WAGNER DE AZEVEDO HERCULANO | J53: OPME
E54: 0403010250 | F54: ='0403010'!B38 -> tratamento cirurgico de fistula liquorica raquidiana | G54: ='0403010'!C38 -> 671.94 | H54: ='por medico'!A17 -> EDUARDO VARJÃO VIEIRA
E55: 0408030267 | F55: ='0408030'!B38 -> artrodese toraco-lombo-sacra posterior 1 nivel | G55: ='0408030'!C38 -> 470
E56: 0408030534 | F56: ='0408030'!B65 -> ressecção de elemento vertebral posterior /postero-lateral /distal a C2 (mais de 2 segmentos) | G56: ='0408030'!C65 -> 345.6
F58: TOTAL | G58: =SUM(G53:G57) -> 3028.1
A59: 9 | B59: JOSE BISPO | C59: 46204 | D59: 20051595 | E59: 0408030100 | F59: ='0408030'!B22 -> artrodese cervical anterior 4 niveis | G59: ='0408030'!C22 -> 1155.78 | H59: ='por medico'!A23 -> ARTUR BASTOS ROCHA | J59: OPME
E60: 0408030640 | F60: ='0408030'!B76 -> revisão de artrodese / tratamento cirurgico de pseudoartrose da coluna cervical anterior | G60: ='0408030'!C76 -> 470 | H60: ='por medico'!A17 -> EDUARDO VARJÃO VIEIRA
E61: 0408030518 | F61: ='0408030'!B63 -> ressecção de 2 ou mais corpos vertebrais toraco-lombo-sacros | G61: ='0408030'!C63 -> 611
F64: TOTAL | G64: =SUM(G59:G63) -> 2236.78
A65: 10 | B65: GERSON DOS SANTOS BASTOS | C65: 46204 | D65: 20166112 | E65: 0403010195 | F65: ='0403010'!B31 -> tratamento cirurgico de abcesso intracraniano | G65: ='0403010'!C31 -> 559.95 | H65: ='por medico'!A17 -> EDUARDO VARJÃO VIEIRA
E66: 0403010179 | F66: ='0403010'!B29 -> retirada de placa de cranioplastia | G66: ='0403010'!C29 -> 391.86 | H66: ='por medico'!A23 -> ARTUR BASTOS ROCHA
F70: TOTAL | G70: =SUM(G65:G69) -> 951.81
A71: 11 | B71: DILMARCI BRANDÃO DE OLIVEIRA | C71: 46572 | D71: 15673171 | E71: 0403020018 | F71: ='0403020'!B13 -> enxerto microcirurgico de nervo periferico ( 2 ou mais nervos) | G71: ='0403020'!C13 -> 500.5 | H71: ='por medico'!A19 -> PEDRO HENRIQUE V. PONDÉ DE SENA
E72: 0403020042 | F72: ='0403020'!B16 -> microcirurgia de plexo braquial com microenxertia | G72: ='0403020'!C16 -> 441.84 | H72: ='por medico'!A23 -> ARTUR BASTOS ROCHA
E73: 0403020069 | F73: ='0403020'!B18 -> microneurrafia | G73: ='0403020'!C18 -> 321.75
E74: 0403020115 | F74: ='0403020'!B23 -> tratamento cirurgico de neuropatia compressiva com ou sem microcirurgia | G74: ='0403020'!C23 -> 560
E75: 0403020050 | F75: ='0403020'!B17 -> microneurolise de nervo periferico | G75: ='0403020'!C17 -> 214.5
F76: TOTAL | G76: =SUM(G71:G75) -> 2038.59
A77: 12 | B77: SILVIO PEREIRA GOMES | C77: 46206 | D77: 10477966 | E77: 0303040041 | F77: ='outros codigos'!B71 -> Tratamento Clinico de Abscesso Cerebral | G77: ='outros codigos'!C71 -> 84.36 | H77: ='por medico'!A21 -> WAGNER DE AZEVEDO HERCULANO | J77: OPME
H78: ='por medico'!A23 -> ARTUR BASTOS ROCHA
F82: TOTAL | G82: =SUM(G77:G81) -> 84.36
A83: 13 | B83: JOSEILDA LIRA DA SILVA | C83: 46208 | D83: 10274421 | E83: 0403030129 | F83: ='0403030'!B23 -> microcirurgia de tumor de base do cranio | G83: ='0403030'!C23 -> 1865.92 | H83: ='por medico'!A21 -> WAGNER DE AZEVEDO HERCULANO | J83: OPME
E84: 0403010241 | F84: ='0403010'!B37 -> tratamento cirurgico de fistula liquorica craniana | G84: ='0403010'!C37 -> 671.94 | H84: ='por medico'!A14 -> CAMILA MOURA DE SOUSA
E85: 0403010144 | F85: ='0403010'!B26 -> reconstução craniama /cranio-facial | G85: ='0403010'!C26 -> 671.94
E86: 0403030048 | F86: ='0403030'!B16 -> Craniotomia para retirada de tumor intracraniano | G86: ='0403030'!C16 -> 554.4
F88: TOTAL | G88: =SUM(G83:G87) -> 3764.2
A89: 14 | B89: IG JOSE KLEBIO DE ALMEIDA SOUZA | C89: 46209 | D89: 20319273 | E89: 0403010241 | F89: ='0403010'!B37 -> tratamento cirurgico de fistula liquorica craniana | G89: ='0403010'!C37 -> 671.94 | H89: ='por medico'!A14 -> CAMILA MOURA DE SOUSA | J89: OPME
E90: 0403010144 | F90: ='0403010'!B26 -> reconstução craniama /cranio-facial | G90: ='0403010'!C26 -> 671.94 | H90: ='por medico'!A21 -> WAGNER DE AZEVEDO HERCULANO
E91: 0403010284 | F91: ='0403010'!B41 -> tratamento cirurgico de hematoma intracerebral | G91: ='0403010'!C41 -> 488.99
F94: TOTAL | G94: =SUM(G89:G93) -> 1832.87
A95: 15 | B95: MARICLEIDE LINARD DE LIMA DE PAULA | C95: 46211 | D95: 20275442 | E95: 0403040116 | F95: ='0403040'!B21 -> microcirurgia para aneurisma da circulaço cerebral anterior menor que 1,5 cm | G95: ='0403040'!C21 -> 1568 | H95: ='por medico'!A15 -> JAQUISSON DE DEUS GUIMARÃES FILHO | J95: OPME
E96: 0403010241 | F96: ='0403010'!B37 -> tratamento cirurgico de fistula liquorica craniana | G96: ='0403010'!C37 -> 671.94 | H96: ='por medico'!A21 -> WAGNER DE AZEVEDO HERCULANO
E97: 0403010144 | F97: ='0403010'!B26 -> reconstução craniama /cranio-facial | G97: ='0403010'!C26 -> 671.94
F100: TOTAL | G100: =SUM(G95:G99) -> 2911.88
A101: 16 | B101: VALDIREI DIAS DA ROCHA | C101: 46212 | D101: 4234761 | E101: 0408030267 | F101: ='0408030'!B38 -> artrodese toraco-lombo-sacra posterior 1 nivel | G101: ='0408030'!C38 -> 470 | H101: ='por medico'!A21 -> WAGNER DE AZEVEDO HERCULANO | J101: OPME
E102: 0408030135 | F102: ='0408030'!B25 -> artrodese intersomatica vias posterior /postero lateral 1 nivel | G102: ='0408030'!C25 -> 611 | H102: ='por medico'!A17 -> EDUARDO VARJÃO VIEIRA
E103: 0408030380 | F103: ='0408030'!B51 -> disectomia cervical/lombar/lombo-sacra por via posterior (1 nivel com microscopio) | G103: ='0408030'!C51 -> 470
E104: 0403020115 | F104: ='0403020'!B23 -> tratamento cirurgico de neuropatia compressiva com ou sem microcirurgia | G104: ='0403020'!C23 -> 560
F106: TOTAL | G106: =SUM(G101:G105) -> 2111
A107: 17 | B107: ANDRADE DE NOVAIS SANTOS | C107: 46207 | D107: 29297966 | E107: 0408030054 | F107: ='0408030'!B17 -> artrodese cervical /cervico toráxica posterior 3 niveis | G107: ='0408030'!C17 -> 1155.78 | H107: ='por medico'!A23 -> ARTUR BASTOS ROCHA | J107: OPME
E108: 0403010250 | F108: ='0403010'!B38 -> tratamento cirurgico de fistula liquorica raquidiana | G108: ='0403010'!C38 -> 671.94 | H108: ='por medico'!A19 -> PEDRO HENRIQUE V. PONDÉ DE SENA
E109: 0403020115 | F109: ='0403020'!B23 -> tratamento cirurgico de neuropatia compressiva com ou sem microcirurgia | G109: ='0403020'!C23 -> 560
E110: 0408030534 | F110: ='0408030'!B65 -> ressecção de elemento vertebral posterior /postero-lateral /distal a C2 (mais de 2 segmentos) | G110: ='0408030'!C65 -> 345.6
F112: TOTAL | G112: =SUM(G107:G111) -> 2733.32
A113: 18 | B113: ANTONIO SIMOES DA CONCEIÇÃO | C113: 46211 | D113: 20329637 | E113: 0403010314 | F113: ='0403010'!B44 -> Tratamento cirurgico de hematoma subdural cronico | G113: ='0403010'!C44 -> 682.08 | H113: ='por medico'!A23 -> ARTUR BASTOS ROCHA | J113: OPME
E114: 0403010098 | F114: ='0403010'!B21 -> derivação ventricular externa -subgaleal externa | G114: ='0403010'!C21 -> 286 | H114: ='por medico'!A21 -> WAGNER DE AZEVEDO HERCULANO
E115: 0403010365 | F115: ='0403010'!B49 -> trepanação craniana para punção ou biopsia | G115: ='0403010'!C49 -> 107.52
F118: TOTAL | G118: =SUM(G113:G117) -> 1075.6
A119: 19 | B119: RAIMUNDO DOS SANTOS MORAES | C119: 46209 | D119: 20313573 | E119: 0403010012 | F119: ='0403010'!B13 -> Cranioplastia | G119: ='0403010'!C13 -> 522.48 | H119: ='por medico'!A14 -> CAMILA MOURA DE SOUSA | J119: OPME
E120: 0403010314 | F120: ='0403010'!B44 -> Tratamento cirurgico de hematoma subdural cronico | G120: ='0403010'!C44 -> 682.08 | H120: ='por medico'!A21 -> WAGNER DE AZEVEDO HERCULANO
E121: 0403010098 | F121: ='0403010'!B21 -> derivação ventricular externa -subgaleal externa | G121: ='0403010'!C21 -> 286
E122: 0403010020 | F122: ='0403010'!B14 -> Craniotomia descompressiva | G122: ='0403010'!C14 -> 391.86
E123: 0403010365 | F123: ='0403010'!B49 -> trepanação craniana para punção ou biopsia | G123: ='0403010'!C49 -> 107.52
F124: TOTAL | G124: =G119+G120+G121+G122+G123 -> 1989.94
A125: 20 | B125: WELLINGTON ALVES DA SILVA | C125: 46210 | D125: 20338463 | E125: 0403010110 | F125: ='0403010'!B23 -> descompressão de orbita por doença ou trauma | G125: ='0403010'!C23 -> 786.5 | H125: ='por medico'!A19 -> PEDRO HENRIQUE V. PONDÉ DE SENA | J125: OPME
E126: 0403010241 | F126: ='0403010'!B37 -> tratamento cirurgico de fistula liquorica craniana | G126: ='0403010'!C37 -> 671.94 | H126: ='por medico'!A14 -> CAMILA MOURA DE SOUSA
E127: 0403010292 | F127: ='0403010'!B42 -> tratamento cirurgico de hematoma intracerebral (tecnica complementar) | G127: ='0403010'!C42 -> 682.08
E128: 0403010144 | F128: ='0403010'!B26 -> reconstução craniama /cranio-facial | G128: ='0403010'!C26 -> 671.94
E129: 0403010268 | F129: ='0403010'!B39 -> tratamento cirurgico de fratura do craniano com afundamento | G129: ='0403010'!C39 -> 391.86
F130: TOTAL | G130: =SUM(G125:G129) -> 3204.32
A131: 21 | B131: CICERO PEDRO DA SILVA | C131: 46207 | D131: 18069914 | E131: 0408030291 | F131: ='0408030'!B42 -> artrodese toraco-lombo-sacra posterior 2 niveis | G131: ='0408030'!C42 -> 1155.78 | H131: ='por medico'!A21 -> WAGNER DE AZEVEDO HERCULANO | J131: OPME
H132: ='por medico'!A14 -> CAMILA MOURA DE SOUSA
F136: TOTAL | G136: =SUM(G131:G135) -> 1155.78
A137: 22 | B137: EMILY MARLENE MACHADO | C137: 46215 | D137: 20428447 | E137: 0408030275 | F137: ='0408030'!B40 -> artrodese toraco-lombo-sacra posterior 3 niveis | G137: ='0408030'!C40 -> 1155.78 | H137: ='por medico'!A23 -> ARTUR BASTOS ROCHA | J137: OPME
...

Sheet por medico
A1: GOVERNO DO ESTADO DA BAHIA
A2: Secretaria da Saúde do Estado da Bahia – SESAB
A3: Hospital Geral Clériston Andrade - HGCA
A6: De: Contas Hospitalares
A7: Para: Diretoria Médica/ Coordenação Neurologia
A9: Relatório de Pacientes que realizaram neurocirurgia no HGCA
A10: DATA:
A13: Profissional | B13: frequencia mensal | C13: Valor SP SIGITAP
A14: CAMILA MOURA DE SOUSA | B14: =COUNTIF('JULHO 2026'!H11:H599,'por medico'!A14)+COUNTIF('JULHO 2026'!H605:H1030,'por medico'!A14) -> 32
A15: JAQUISSON DE DEUS GUIMARÃES FILHO | B15: =COUNTIF('JULHO 2026'!H11:H599,'por medico'!A15)+COUNTIF('JULHO 2026'!H605:H1030,'por medico'!A15) -> 10
A16: LUIZ AUGUSTO MEDRADO SOEIRO | B16: =COUNTIF('JULHO 2026'!H11:H599,'por medico'!A16)+COUNTIF('JULHO 2026'!H605:H1030,'por medico'!A16) -> 4
A17: EDUARDO VARJÃO VIEIRA | B17: =COUNTIF('JULHO 2026'!H11:H599,'por medico'!A17)+COUNTIF('JULHO 2026'!H605:H1030,'por medico'!A17) -> 26
A18: DOUGLAS L. TRAVASSOS | B18: =COUNTIF('JULHO 2026'!H11:H599,'por medico'!A18)+COUNTIF('JULHO 2026'!H605:H1030,'por medico'!A18) -> 0
A19: PEDRO HENRIQUE V. PONDÉ DE SENA | B19: =COUNTIF('JULHO 2026'!H11:H599,'por medico'!A19)+COUNTIF('JULHO 2026'!H605:H1030,'por medico'!A19) -> 12
A20: ALLAN FRANÇA ALVES | B20: =COUNTIF('JULHO 2026'!H11:H599,'por medico'!A20)+COUNTIF('JULHO 2026'!H605:H1030,'por medico'!A20) -> 0
A21: WAGNER DE AZEVEDO HERCULANO | B21: =COUNTIF('JULHO 2026'!H11:H599,'por medico'!A21)+COUNTIF('JULHO 2026'!H605:H1030,'por medico'!A21) -> 48
A22: ISRAEL MARQUES NETO | B22: =COUNTIF('JULHO 2026'!H11:H599,'por medico'!A22)+COUNTIF('JULHO 2026'!H605:H1030,'por medico'!A22) -> 0
A23: ARTUR BASTOS ROCHA | B23: =COUNTIF('JULHO 2026'!H11:H599,'por medico'!A23)+COUNTIF('JULHO 2026'!H605:H1030,'por medico'!A23) -> 35
A24: IOGO HENRIQUE DE O. ARAUJO | B24: =COUNTIF('JULHO 2026'!H11:H599,'por medico'!A24)+COUNTIF('JULHO 2026'!H605:H1030,'por medico'!A24) -> 3
A25: MARCIO BRANDÃO | B25: =COUNTIF('JULHO 2026'!H11:H599,'por medico'!A25)+COUNTIF('JULHO 2026'!H605:H1030,'por medico'!A25) -> 0
A26: ANTONIO GUTEMBERG DE SOUZA MARTINS | B26: =COUNTIF('JULHO 2026'!H11:H599,'por medico'!A26)+COUNTIF('JULHO 2026'!H605:H1030,'por medico'!A26) -> 0
A27: LUCAS CHAVES LELIS | B27: =COUNTIF('JULHO 2026'!H11:H599,'por medico'!A27)+COUNTIF('JULHO 2026'!H605:H1030,'por medico'!A27) -> 0
A28: total procedimentos | B28: =SUM(B14:B27) -> 170 | C28: =SUM(C14:C27) -> 0
A32: Profissional | B32: frequencia mensal | C32: Valor SP SIGITAP
A47: total procedimentos | B47: =SUM(B33:B46) -> 0 | C47: =SUM(C33:C46) -> 0

Sheet Planilha8

Sheet Planilha9

Sheet Planilha10

Sheet Planilha11

Sheet Planilha12

Sheet Planilha13

Sheet Planilha14

Sheet 0403010
A1: GOVERNO DO ESTADO DA BAHIA
A2: Secretaria da Saúde do Estado da Bahia – SESAB
A3: Hospital Geral Clériston Andrade - HGCA
A6: De: Contas Hospitalares
A7: Para: Diretoria Médica/ Coordenação Neurologia
A9: Relatório de Pacientes que realizaram neurocirurgia no HGCA .
A10: data:
A12: Codigo | B12: Nome | C12: valor | D12: quantidade mês | E12: gastos
A13: 040301001-2 | B13: Cranioplastia | C13: 522.48 | D13: ='CALCULOS EXTRAS'!A6 -> 0 | E13: =D13*C13 -> 0
A14: 040301002-0 | B14: Craniotomia descompressiva | C14: 391.86 | D14: ='CALCULOS EXTRAS'!A7 -> 0 | E14: =D14*C14 -> 0
A15: 040301003-9 | B15: Craniotomia descompressiva da fossa posterior | C15: 391.86 | D15: ='CALCULOS EXTRAS'!A8 -> 0 | E15: =D15*C15 -> 0
A16: 040301004-7 | B16: Craniotomia para retirada de cisto/ abcesso/granuloma encefalico | C16: 671.94 | D16: ='CALCULOS EXTRAS'!A9 -> 0 | E16: =D16*C16 -> 0
A17: 040301005-5 | B17: Craniotomia para retirada de cisto/ abcesso/granuloma encefalico(tecnica complementar) | C17: 671.94 | D17: ='CALCULOS EXTRAS'!A10 -> 0 | E17: =D17*C17 -> 0
A18: 040301006-3 | B18: Craniotomia para retirada de corpo estranho intracraniano | C18: 682.08 | D18: ='CALCULOS EXTRAS'!A11 -> 0 | E18: =D18*C18 -> 0
A19: 040301007-1 | B19: Craniotomia para retirada de corpo estranho intracraniano(tecnica complementar) | C19: 957.6 | D19: ='CALCULOS EXTRAS'!A12 -> 0 | E19: =D19*C19 -> 0
A20: 040301008-0 | B20: derivação raque-peritoneal | C20: 559.82 | D20: ='CALCULOS EXTRAS'!A13 -> 0 | E20: =D20*C20 -> 0
A21: 040301009-8 | B21: derivação ventricular externa -subgaleal externa | C21: 286 | D21: ='CALCULOS EXTRAS'!A14 -> 0 | E21: =D21*C21 -> 0
A22: 040301010-1 | B22: derivação ventricular para peritoneo/atrio/pleura/raque | C22: 682.08 | D22: ='CALCULOS EXTRAS'!A15 -> 0 | E22: =D22*C22 -> 0
A23: 040301011-0 | B23: descompressão de orbita por doença ou trauma | C23: 786.5 | D23: ='CALCULOS EXTRAS'!A16 -> 0 | E23: =D23*C23 -> 0
A24: 040301012-8 | B24: microcirurgia cerebral endoscopica | C24: 1399.44 | D24: ='CALCULOS EXTRAS'!A17 -> 0 | E24: =D24*C24 -> 0
... A35: 040301023-3 | B35: tratamento cirurgico de disrafismo oculto | C35: 534.24 | D35: ='CALCULOS EXTRAS'!A28 -> 0 | E35: =D35*C35 -> 0
A36: Codigo | B36: Nome | C36: valor | D36: quantidade mês | E36: gastos
A37: 040301024-1 | B37: tratamento cirurgico de fistula liquorica craniana | C37: 671.94 | D37: ='CALCULOS EXTRAS'!A29 -> 0 | E37: =D37*C37 -> 0
A38: 040301025-0 | B38: tratamento cirurgico de fistula liquorica raquidiana | C38: 671.94 | D38: ='CALCULOS EXTRAS'!A30 -> 0 | E38: =D38*C38 -> 0
A39: 040301026-8 | B39: tratamento cirurgico de fratura do craniano com afundamento | C39: 391.86 | D39: ='CALCULOS EXTRAS'!A31 -> 0 | E39: =D39*C39 -> 0
A40: 040301027-6 | B40: tratamento cirurgico de hematoma extradural | C40: 682.08 | D40: ='CALCULOS EXTRAS'!A32 -> 0 | E40: =D40*C40 -> 0
A41: 040301028-4 | B41: tratamento cirurgico de hematoma intracerebral | C41: 488.99 | D41: ='CALCULOS EXTRAS'!A33 -> 0 | E41: =D41*C41 -> 0
A42: 040301029-2 | B42: tratamento cirurgico de hematoma intracerebral (tecnica complementar) | C42: 682.08 | D42: ='CALCULOS EXTRAS'!A34 -> 0 | E42: =D42*C42 -> 0
A43: 040301030-6 | B43: Tratamento cirurgico de hematoma subdural agudo | C43: 682.08 | D43: ='CALCULOS EXTRAS'!A35 -> 0 | E43: =D43*C43 -> 0
A44: 040301031-4 | B44: Tratamento cirurgico de hematoma subdural cronico | C44: 682.08 | D44: ='CALCULOS EXTRAS'!A36 -> 0 | E44: =D44*C44 -> 0
A45: 040301032-2 | B45: Tratamento cirurgico de osteomielite do cranio | C45: 391.86 | D45: ='CALCULOS EXTRAS'!A37 -> 0 | E45: =D45*C45 -> 0
A46: 040301033-0 | B46: Tratamento cirurgico de plastibasia e malformação de arnold chiari | C46: 559.95 | D46: ='CALCULOS EXTRAS'!A38 -> 0 | E46: =D46*C46 -> 0
A47: 040301034-9 | B47: trepanação craniana para propedeutica neurocirurgica/implante para monitoração pic | C47: 107.52 | D47: ='CALCULOS EXTRAS'!A39 -> 0 | E47: =D47*C47 -> 0
A48: 040301035-7 | B48: trepanação craniana para punção ou biopsia (tecnica complementar) | C48: 286 | D48: ='CALCULOS EXTRAS'!A40 -> 0 | E48: =D48*C48 -> 0
... A50: 040301039-0 | B50: drenagem liquorica lombar externa | C50: 858 | D50: ='CALCULOS EXTRAS'!A42 -> 0 | E50: =D50*C50 -> 0
B51: Total | D51: =SUM(D13:D35)+SUM(D37:D50) -> 0 | E51: =SUM(E13:E35)+SUM(E37:E50) -> 0

Sheet 0408030
A1: GOVERNO DO ESTADO DA BAHIA
A2: Secretaria da Saúde do Estado da Bahia – SESAB
A3: Hospital Geral Clériston Andrade - HGCA
A6: De: Contas Hospitalares
A7: Para: Diretoria Médica/ Coordenação Neurologia
A9: Relatório de Pacientes que realizaram neurocirurgia no HGCA em agosto de 2023 .
A10: DATA:
A12: Codigo | B12: Nome | C12: valor | D12: quantidade mês | E12: gastos
A13: 040803001-1 | B13: artrodese cervical /cervico toráxica posterior 5 niveis | C13: 1155.78 | D13: ='CALCULOS EXTRAS'!B6 -> 0 | E13: =D13*C13 -> 0
A14: 040803002-0 | B14: artrodese cervical /cervico toráxica posterior 1 nivel | C14: 611 | D14: ='CALCULOS EXTRAS'!B7 -> 0 | E14: =D14*C14 -> 0
A15: 040803003-8 | B15: artrodese cervical /cervico toráxica posterior 2 niveis | C15: 470 | D15: ='CALCULOS EXTRAS'!B8 -> 0 | E15: =D15*C15 -> 0
A16: 040803004-6 | B16: artrodese cervical /cervico toráxica posterior 6 niveis | C16: 350 | D16: ='CALCULOS EXTRAS'!B9 -> 0 | E16: =D16*C16 -> 0
A17: 040803005-4 | B17: artrodese cervical /cervico toráxica posterior 3 niveis | C17: 1155.78 | D17: ='CALCULOS EXTRAS'!B10 -> 0 | E17: =D17*C17 -> 0
A18: 040803006-2 | B18: artrodese cervical anterior 3 niveis | C18: 611 | D18: ='CALCULOS EXTRAS'!B11 -> 0 | E18: =D18*C18 -> 0
A19: 040803007-0 | B19: artrodese cervical anterior 2 niveis | C19: 470 | D19: ='CALCULOS EXTRAS'!B12 -> 0 | E19: =D19*C19 -> 0
A20: 040803008-9 | B20: artrodese cervical anterior C1-C2 via trans-oral/extra oral | C20: 638.76 | D20: ='CALCULOS EXTRAS'!B13 -> 0 | E20: =D20*C20 -> 0
A21: 040803009-7 | B21: artrodese cervical anterior 5 niveis | C21: 1155.78 | D21: ='CALCULOS EXTRAS'!B14 -> 0 | E21: =D21*C21 -> 0
A22: 040803010-0 | B22: artrodese cervical anterior 4 niveis | C22: 1155.78 | D22: ='CALCULOS EXTRAS'!B15 -> 0 | E22: =D22*C22 -> 0
A23: 040803011-9 | B23: artrodese cervical anterior 1 nivel | C23: 470 | D23: ='CALCULOS EXTRAS'!B16 -> 0 | E23: =D23*C23 -> 0
A24: 040803012-7 | B24: artrodese cervical posterior C1-C2 | C24: 470 | D24: ='CALCULOS EXTRAS'!B17 -> 0 | E24: =D24*C24 -> 0
... A38: 040803026-7 | B38: artrodese toraco-lombo-sacra posterior 1 nivel | C38: 470 | D38: ='CALCULOS EXTRAS'!B31 -> 0 | E38: =D38*C38 -> 0
A39: Codigo | B39: Nome | C39: valor | D39: quantidade mês | E39: gastos
A40: 040803027-5 | B40: artrodese toraco-lombo-sacra posterior 3 niveis | C40: 1155.78 | D40: ='CALCULOS EXTRAS'!B32 -> 0 | E40: =D40*C40 -> 0
A41: 040803028-3 | B41: artrodese toraco-lombo-sacra posterior 5 niveis | C41: 1155.78 | D41: ='CALCULOS EXTRAS'!B33 -> 0 | E41: =D41*C41 -> 0
A42: 040803029-1 | B42: artrodese toraco-lombo-sacra posterior 2 niveis | C42: 1155.78 | D42: ='CALCULOS EXTRAS'!B34 -> 0 | E42: =D42*C42 -> 0
A43: 040803030-5 | B43: artrodese toraco-lombo-sacra posterior 4 niveis | C43: 1155.78 | D43: ='CALCULOS EXTRAS'!B35 -> 0 | E43: =D43*C43 -> 0
A44: 040803031-3 | B44: artrodese toraco-lombo-sacra posterior 6 niveis | C44: 1155.78 | D44: ='CALCULOS EXTRAS'!B36 -> 0 | E44: =D44*C44 -> 0
A45: 040803032-1 | B45: artrodese toraco-lombo-sacra posterior 7 niveis | C45: 1155.78 | D45: ='CALCULOS EXTRAS'!B37 -> 0 | E45: =D45*C45 -> 0
A46: 040803033-0 | B46: costo -transversectomia | C46: 328.44 | D46: ='CALCULOS EXTRAS'!B38 -> 0 | E46: =D46*C46 -> 0
A47: 040803034-8 | B47: cotoplastia (3 ou mais costelas) | C47: 328.44 | D47: ='CALCULOS EXTRAS'!B39 -> 0 | E47: =D47*C47 -> 0
A48: 040803035-6 | B48: descompressão da junção cranio cervical via transoral/retrofaringea | C48: 830 | D48: ='CALCULOS EXTRAS'!B40 -> 0 | E48: =D48*C48 -> 0
A49: 040803036-4 | B49: descompressão ossea na junção cranio cervical vias posterior | C49: 470 | D49: ='CALCULOS EXTRAS'!B41 -> 0 | E49: =D49*C49 -> 0
A50: 040803037-2 | B50: descompressão ossea na junção cranio cervical vias posterior com duroplastia | C50: 611 | D50: ='CALCULOS EXTRAS'!B42 -> 0 | E50: =D50*C50 -> 0
A51: 040803038-0 | B51: disectomia cervical/lombar/lombo-sacra por via posterior (1 nivel com microscopio) | C51: 470 | D51: ='CALCULOS EXTRAS'!B43 -> 0 | E51: =D51*C51 -> 0
... A76: 040803064-0 | B76: revisão de artrodese / tratamento cirurgico de pseudoartrose da coluna cervical anterior | C76: 470 | D76: ='CALCULOS EXTRAS'!B68 -> 0 | E76: =D76*C76 -> 0
A77: Codigo | B77: Nome | C77: valor | D77: quantidade mês | E77: gastos
A78: 040803065-8 | B78: tratamento cirurgico de deformidade da coluna via antero - posterior 9 ou mais niveis | C78: 1656.01 | D78: ='CALCULOS EXTRAS'!B69 -> 0 | E78: =D78*C78 -> 0
A79: 040803066-6 | B79: tratamento cirurgico de deformidade da coluna via anterior 8 niveis | C79: 1435.21 | D79: ='CALCULOS EXTRAS'!B70 -> 0 | E79: =D79*C79 -> 0
A80: 040803067-4 | B80: tratamento cirurgico de deformidade da coluna via anterior 4 niveis | C80: 470 | D80: ='CALCULOS EXTRAS'!B71 -> 0 | E80: =D80*C80 -> 0
A81: 040803068-2 | B81: tratamento cirurgico de deformidade da coluna via anterior 5 niveis | C81: 611 | D81: ='CALCULOS EXTRAS'!B72 -> 0 | E81: =D81*C81 -> 0
A82: 040803069-0 | B82: tratamento cirurgico de deformidade da coluna via anterior posterior até 8 niveis | C82: 874.95 | D82: ='CALCULOS EXTRAS'!B73 -> 0 | E82: =D82*C82 -> 0
A83: 040803070-4 | B83: vertebroplastia por dispositivo guiado em 1 nivel | C83: 230 | D83: ='CALCULOS EXTRAS'!B74 -> 0 | E83: =D83*C83 -> 0
A84: 040803071-2 | B84: tratamento cirurgico de deformidade da coluna via anterior 6 niveis | C84: 1155.12 | D84: ='CALCULOS EXTRAS'!B75 -> 0 | E84: =D84*C84 -> 0
A85: 040803072-0 | B85: tratamento cirurgico de deformidade da coluna via anterior 7 niveis | C85: 874.95 | D85: ='CALCULOS EXTRAS'!B76 -> 0 | E85: =D85*C85 -> 0
A86: 040803073-9 | B86: tratamento cirurgico de deformidade da coluna via posterior 8 niveis | C86: 874.95 | D86: ='CALCULOS EXTRAS'!B77 -> 0 | E86: =D86*C86 -> 0
A87: 040803074-7 | B87: tratamento cirurgico de fratura C1-C2 por via anterior (osteossintese) | C87: 470 | D87: ='CALCULOS EXTRAS'!B78 -> 0 | E87: =D87*C87 -> 0
A88: 040803075-5 | B88: tratamento cirurgico de torcicolo congenito | C88: 133.35 | D88: ='CALCULOS EXTRAS'!B79 -> 0 | E88: =D88*C88 -> 0
A89: 040803076-3 | B89: tratamento cirurgico de deformidade da coluna via posterior 9 niveis | C89: 1435.21 | D89: ='CALCULOS EXTRAS'!B80 -> 0 | E89: =D89*C89 -> 0
... A104: 040803091-7 | B104: artrodese cervical /cervico toráxica posterior 4 niveis | C104: 1155.78 | D104: ='CALCULOS EXTRAS'!B95 -> 0 | E104: =D104*C104 -> 0
B105: Total | D105: =SUM(D13:D38)+SUM(D40:D76)+SUM(D78:D104) -> 0 | E105: =SUM(E13:E38)+SUM(E40:E76)+SUM(E78:E104) -> 0

Sheet 0403020
A1: GOVERNO DO ESTADO DA BAHIA
A2: Secretaria da Saúde do Estado da Bahia – SESAB
A3: Hospital Geral Clériston Andrade - HGCA
A6: De: Contas Hospitalares
A7: Para: Diretoria Médica/ Coordenação Neurologia
A9: Relatório de Pacientes que realizaram neurocirurgia no HGCA
A10: DATA:
A12: Codigo | B12: Nome | C12: valor | D12: quantidade mês | E12: gastos
A13: 040302001-8 | B13: enxerto microcirurgico de nervo periferico ( 2 ou mais nervos) | C13: 500.5 | D13: ='CALCULOS EXTRAS'!C6 -> 0 | E13: =D13*C13 -> 0
A14: 040302002-6 | B14: enxerto microcirurgico de nervo periferico ( unuco nervo) | C14: 500.5 | D14: ='CALCULOS EXTRAS'!C7 -> 0 | E14: =D14*C14 -> 0
A15: 040302003-4 | B15: microcirurgia de plexo braquial com exploração e neurolise | C15: 230.16 | D15: ='CALCULOS EXTRAS'!C8 -> 0 | E15: =D15*C15 -> 0
A16: 040302004-2 | B16: microcirurgia de plexo braquial com microenxertia | C16: 441.84 | D16: ='CALCULOS EXTRAS'!C9 -> 0 | E16: =D16*C16 -> 0
A17: 040302005-0 | B17: microneurolise de nervo periferico | C17: 214.5 | D17: ='CALCULOS EXTRAS'!C10 -> 0 | E17: =D17*C17 -> 0
A18: 040302006-9 | B18: microneurrafia | C18: 321.75 | D18: ='CALCULOS EXTRAS'!C11 -> 0 | E18: =D18*C18 -> 0
A19: 040302007-7 | B19: neurolise não funcional de nervos perifericos | C19: 180.75 | D19: ='CALCULOS EXTRAS'!C12 -> 0 | E19: =D19*C19 -> 0
A20: 040302008-5 | B20: neurorrafia | C20: 165.17 | D20: ='CALCULOS EXTRAS'!C13 -> 0 | E20: =D20*C20 -> 0
A21: 040302009-3 | B21: neurotomia seletiva de trigemeo e outors nervos cranianos | C21: 559.82 | D21: ='CALCULOS EXTRAS'!C14 -> 0 | E21: =D21*C21 -> 0
A22: 040302010-7 | B22: transposição do nervo cubital | C22: 247.95 | D22: ='CALCULOS EXTRAS'!C15 -> 0 | E22: =D22*C22 -> 0
A23: 040302011-5 | B23: tratamento cirurgico de neuropatia compressiva com ou sem microcirurgia | C23: 560 | D23: ='CALCULOS EXTRAS'!C16 -> 0 | E23: =D23*C23 -> 0
A24: 040302012-3 | B24: tratamento cirurgico de sindrome compressiva de tunel osteo-fibroso ao nivel carpo | C24: 202.44 | D24: ='CALCULOS EXTRAS'!C17 -> 0 | E24: =D24*C24 -> 0
A25: 040302013-1 | B25: tratamento microcirurgico de tumor de nervo periferico /neuroma | C25: 168 | D25: ='CALCULOS EXTRAS'!C18 -> 0 | E25: =D25*C25 -> 0
B26: Total | D26: =SUM(D13:D25) -> 0 | E26: =SUM(E13:E25) -> 0

Sheet 0403030
A1: GOVERNO DO ESTADO DA BAHIA
A2: Secretaria da Saúde do Estado da Bahia – SESAB
A3: Hospital Geral Clériston Andrade - HGCA
A6: De: Contas Hospitalares
A7: Para: Diretoria Médica/ Coordenação Neurologia
A9: Relatório de Pacientes que realizaram neurocirurgia no HGCA
A10: DATA:
A12: Codigo | B12: Nome | C12: valor | D12: quantidade mês | E12: gastos
A13: 040303001-3 | B13: Craniotomia para biopsia encefálica | C13: 500.5 | D13: ='CALCULOS EXTRAS'!D6 -> 0 | E13: =D13*C13 -> 0
A14: 040303002-1 | B14: Craniotomia para biopsia encefálica com técnica complementar | C14: 957.6 | D14: ='CALCULOS EXTRAS'!D7 -> 0 | E14: =D14*C14 -> 0
A15: 040303003-0 | B15: Craniotomia para retirada de tumor cerebral inclusivo da fossa posterior | C15: 1072.5 | D15: ='CALCULOS EXTRAS'!D8 -> 0 | E15: =D15*C15 -> 0
A16: 040303004-8 | B16: Craniotomia para retirada de tumor intracraniano | C16: 554.4 | D16: ='CALCULOS EXTRAS'!D9 -> 0 | E16: =D16*C16 -> 0
A17: 040303005-6 | B17: Craniotomia por tumor osseo | C17: 682.08 | D17: ='CALCULOS EXTRAS'!D10 -> 0 | E17: =D17*C17 -> 0
A18: 040303006-4 | B18: hipofisectomia transesfenoidal por técnica complementar | C18: 1399.44 | D18: ='CALCULOS EXTRAS'!D11 -> 0 | E18: =D18*C18 -> 0
A19: 040303008-0 | B19: microcirurgia de tumor intradural e extramedular | C19: 907.2 | D19: ='CALCULOS EXTRAS'!D12 -> 0 | E19: =D19*C19 -> 0
A20: 040303009-9 | B20: microcirurgia de tumor medular técnica complementar | C20: 1540.56 | D20: ='CALCULOS EXTRAS'!D13 -> 0 | E20: =D20*C20 -> 0
A21: 040303010-2 | B21: microcirurgia de tumor medular | C21: 1041.6 | D21: ='CALCULOS EXTRAS'!D14 -> 0 | E21: =D21*C21 -> 0
A22: 040303011-0 | B22: Microcirurgia para biopsia demedula espinhal ou raizaes | C22: 560.16 | D22: ='CALCULOS EXTRAS'!D15 -> 0 | E22: =D22*C22 -> 0
A23: 040303012-9 | B23: microcirurgia de tumor de base do cranio | C23: 1865.92 | D23: ='CALCULOS EXTRAS'!D16 -> 0 | E23: =D23*C23 -> 0
A24: 040303013-7 | B24: microcirurgia de tumor de orbita | C24: 1072.5 | D24: ='CALCULOS EXTRAS'!D17 -> 0 | E24: =D24*C24 -> 0
... A27: 040303016-1 | B27: ressecção de tumor raquimedular e extradural | C27: 672 | D27: ='CALCULOS EXTRAS'!D20 -> 0 | E27: =D27*C27 -> 0
B28: Total | D28: =SUM(D13:D27) -> 0 | E28: =SUM(E13:E27) -> 0

Sheet 0403040
A1: GOVERNO DO ESTADO DA BAHIA
A2: Secretaria da Saúde do Estado da Bahia – SESAB
A3: Hospital Geral Clériston Andrade - HGCA
A6: De: Contas Hospitalares
A7: Para: Diretoria Médica/ Coordenação Neurologia
A9: Relatório de Pacientes que realizaram neurocirurgia no HGCA
A10: DATA:
A12: Codigo | B12: Nome | C12: valor | D12: quantidade mês | E12: gastos
A13: 040304001-9 | B13: anstomose vascular extras/intracraniana | C13: 1824.74 | D13: ='CALCULOS EXTRAS'!E6 -> 0 | E13: =D13*C13 -> 0
A14: 040304002-7 | B14: descomprenssão neurovascular de nervos cranianos | C14: 1399.44 | D14: ='CALCULOS EXTRAS'!E7 -> 0 | E14: =D14*C14 -> 0
A15: 040304005-1 | B15: microcirurgia para malformação arterio-venosa cerebral | C15: 1209.6 | D15: ='CALCULOS EXTRAS'!E8 -> 0 | E15: =D15*C15 -> 0
A16: 040304006-0 | B16: microcirurgia para malformação arterio-venosa cerebral profunda | C16: 1344 | D16: ='CALCULOS EXTRAS'!E9 -> 0 | E16: =D16*C16 -> 0
A17: 040304007-8 | B17: microcirurgia vascular intracraniana (com tecnica complementar) | C17: 1865.92 | D17: ='CALCULOS EXTRAS'!E10 -> 0 | E17: =D17*C17 -> 0
A18: 040304008-6 | B18: tratamento cirurgico de fistula carotideo-cavernosa | C18: 882 | D18: ='CALCULOS EXTRAS'!E11 -> 0 | E18: =D18*C18 -> 0
A19: 040304009-4 | B19: microcirurgia para aneurisma da circulaço cerebral anterior maior que 1,5 cm | C19: 1568 | D19: ='CALCULOS EXTRAS'!E12 -> 0 | E19: =D19*C19 -> 0
A20: 040304010-8 | B20: microcirurgia para aneurisma da circulaço cerebral posterior maior que 1,5 cm | C20: 2054.08 | D20: ='CALCULOS EXTRAS'!E13 -> 0 | E20: =D20*C20 -> 0
A21: 040304011-6 | B21: microcirurgia para aneurisma da circulaço cerebral anterior menor que 1,5 cm | C21: 1568 | D21: ='CALCULOS EXTRAS'!E14 -> 0 | E21: =D21*C21 -> 0
A22: 040304012-4 | B22: microcirurgia para aneurisma da circulaço cerebral posterior menor que 1,5 cm | C22: 2054.08 | D22: ='CALCULOS EXTRAS'!E15 -> 0 | E22: =D22*C22 -> 0
B23: Total | D23: =SUM(D13:D22) -> 0 | E23: =SUM(E13:E22) -> 0

Sheet 0403050
A1: GOVERNO DO ESTADO DA BAHIA
A2: Secretaria da Saúde do Estado da Bahia – SESAB
A3: Hospital Geral Clériston Andrade - HGCA
A6: De: Contas Hospitalares
A7: Para: Diretoria Médica/ Coordenação Neurologia
A9: Relatório de Pacientes que realizaram neurocirurgia no HGCA
A10: DATA:
A12: Codigo | B12: Nome | C12: valor | D12: quantidade mês | E12: gastos
A13: 040305001-4 | B13: alcoolizaçõa de nervo craniano | C13: 0 | D13: ='CALCULOS EXTRAS'!F6 -> 0 | E13: =D13*C13 -> 0
A14: 040305002-2 | B14: neurolise de trigemeo com glicerol | C14: 0 | D14: ='CALCULOS EXTRAS'!F7 -> 0 | E14: =D14*C14 -> 0
A15: 040305003-0 | B15: bloqueios prolongados de sistema nervoso perferico / central com bomba de infusão | C15: 101.36 | D15: ='CALCULOS EXTRAS'!F8 -> 0 | E15: =D15*C15 -> 0
A16: 040305004-9 | B16: cordotomia /mielotomia por radiofrequencia | C16: 965.25 | D16: ='CALCULOS EXTRAS'!F9 -> 0 | E16: =D16*C16 -> 0
A17: 040305005-7 | B17: implante intratecal de bomba de infusão de farmacos | C17: 607.75 | D17: ='CALCULOS EXTRAS'!F10 -> 0 | E17: =D17*C17 -> 0
A18: 040305006-5 | B18: microcirurgia com cordotomia /mielotomia a ceu aberto | C18: 391.92 | D18: ='CALCULOS EXTRAS'!F11 -> 0 | E18: =D18*C18 -> 0
A19: 040305007-3 | B19: microcirurgia com rizotomia a ceu aberto | C19: 858 | D19: ='CALCULOS EXTRAS'!F12 -> 0 | E19: =D19*C19 -> 0
A20: 040305008-1 | B20: neurotomia percutanea de nervos perofericos por agentes quimicos | C20: 0 | D20: ='CALCULOS EXTRAS'!F13 -> 0 | E20: =D20*C20 -> 0
A21: 040305009-0 | B21: rizotomia percutanea com balão | C21: 536.25 | D21: ='CALCULOS EXTRAS'!F14 -> 0 | E21: =D21*C21 -> 0
A22: 040305010-3 | B22: rizotomia /neurotomia percutanea por radiofrequencia | C22: 607.75 | D22: ='CALCULOS EXTRAS'!F15 -> 0 | E22: =D22*C22 -> 0
A23: 040305011-1 | B23: simpatectomia lombar a ceu berto | C23: 279.03 | D23: ='CALCULOS EXTRAS'!F16 -> 0 | E23: =D23*C23 -> 0
A24: 040305012-0 | B24: simpatectomia lombar videocirurgica | C24: 343.2 | D24: ='CALCULOS EXTRAS'!F17 -> 0 | E24: =D24*C24 -> 0
... A28: 040305016-2 | B28: tratamento ablativo por estereotaxia em estrutura profunca de snc para tratamento de movimentos anormais ou controle da dor | C28: 858 | D28: ='CALCULOS EXTRAS'!F21 -> 0 | E28: =D28*C28 -> 0
B29: Total | D29: =SUM(D13:D28) -> 0 | E29: =SUM(E13:E28) -> 0

Sheet outros codigos
A1: GOVERNO DO ESTADO DA BAHIA
A2: Secretaria da Saúde do Estado da Bahia – SESAB
A3: Hospital Geral Clériston Andrade - HGCA
A6: De: Contas Hospitalares
A7: Para: Diretoria Médica/ Coordenação Neurologia
A9: Relatório de Pacientes que realizaram neurocirurgia no HGCA em agosto de 2023 .
A12: Codigo | B12: Nome | C12: valor | D12: quantidade mês | E12: gastos
A13: 040806062-0 | B13: Tratamento cirurgico de infecções pós artroplastia (grandes articulações) | C13: 232.77 | D13: ='CALCULOS EXTRAS'!G6 -> 0 | E13: =D13*C13 -> 0
A14: 041504003-5 | B14: Debridamento de ulcera/ de tecidos desvitalizados | C14: 215.91 | D14: ='CALCULOS EXTRAS'!G7 -> 0 | E14: =D14*C14 -> 0
A15: 040806037-9 | B15: Retirada de placa e/ou parafusos | C15: 61.56 | D15: ='CALCULOS EXTRAS'!G8 -> 0 | E15: =D15*C15 -> 0
A16: 020101013-5 | B16: Biopsia de copro vertebral lamina e pediculo vertebral ( por dispositivo guiado) | C16: 278.61 | D16: ='CALCULOS EXTRAS'!G9 -> 0 | E16: =D16*C16 -> 0
A17: 040804021-1 | B17: Retirada de enxerto autógeno de ilíaco | C17: 0 | D17: ='CALCULOS EXTRAS'!G10 -> 0 | E17: =D17*C17 -> 0
A18: 040306008-7 | B18: Microcirurgia para ressecção unilobar extratemporal sem monitoramentointra-operatório | C18: 1118.52 | D18: ='CALCULOS EXTRAS'!G11 -> 0 | E18: =D18*C18 -> 0
A19: 020101025-9 | B19: Biopsia de lamin pediculo e processos vertebrais | C19: 115.02 | D19: ='CALCULOS EXTRAS'!G12 -> 0 | E19: =D19*C19 -> 0
A20: 040806004-2 | B20: amputação/ desarticulação de deo | C20: 109.8 | D20: ='CALCULOS EXTRAS'!G13 -> 0 | E20: =D20*C20 -> 0
A21: 040806009-3 | B21: descompressão com esvaziamento medular por brocagem/via corticotomia | C21: 215.59 | D21: ='CALCULOS EXTRAS'!G14 -> 0 | E21: =D21*C21 -> 0
A22: 020101025-9 | B22: Biopsia de lamin pediculo e processos vertebrais | C22: 115.02 | D22: ='CALCULOS EXTRAS'!G15 -> 0 | E22: =D22*C22 -> 0
A23: 040806004-2 | B23: amputação/ desarticulação de dedo | C23: 109.8 | D23: ='CALCULOS EXTRAS'!G16 -> 0 | E23: =D23*C23 -> 0
A24: 041204016-6 | B24: TORACOSTOMIA COM DRENAGEM PLEURAL FECHADA | C24: 1029.44 | D24: ='CALCULOS EXTRAS'!G17 -> 0 | E24: =D24*C24 -> 0
... A37: 040704016-1 | B37: LAPAROTOMIA EXPLORADORA | C37: 139.99 | D37: ='CALCULOS EXTRAS'!G30 | E37: =D37*C37 -> 0
B38: TTO lesão do Sist. neurovegetativo p/ ag. quimicos | E38: =D38*C38 -> 0
A39: 040806014-0 | B39: FASCIOTOMIA | E39: =D39*C39 -> 0
A40: 040806031-0 | B40: Resseccção Simples de Tumor Osseo / de partes moles | C40: 117.9 | E40: =D40*C40 -> 0
A41: 040306004-4 | B41: Microcirurgia para Lesionectomia sem Monitoramento Intra-Operatório | C41: 1118.52 | E41: =D41*C41 -> 0
A42: 040402051-8 | B42: Osteossintese de Fratura Complexa da Mandibula | C42: 186.66 | E42: =D42*C42 -> 0
A43: 040901008-1 | B43: CISTORRAFIA | C43: 160.04 | E43: =D43*C43 -> 0
A44: 040802034-2 | B44: Tratamento cirurgico de fratura/lesão fisaria das falanges da mão (com fixação) | C44: 92.91 | E44: =D44*C44 -> 0
A45: 040805054-3 | B45: Tratamento cirurgico de fratura do pilão tibial | C45: 202.95 | E45: =D45*C45 -> 0
A46: 040402052-6 | B46: Osteossintese de Fratura do Complexo orbito-zigomatico-maxilar | C46: 170.76 | E46: =D46*C46 -> 0
A47: 040602016-7 | B47: FASCIOTOMIA P/ DESCOMPRESSÃO | C47: 215.91 | E47: =D47*C47 -> 0
A48: 040102002-9 | B48: Enxerto Dermo-Epidérmico | C48: 115.51 | E48: =D48*C48 -> 0
A49: 040806031-0 | B49: Ressecção Simple de Tumor Ósseo/ de partes moles | C49: 250.13 | E49: =D49*C49 -> 0
A50: 040806034-4 | B50: RETIRADA DE ESPAÇADORE/E OUTROS MATERIAIS | C50: 55.96 | E50: =D50*C50 -> 0
A51: 040401051-2 | B51: SINUSOTOMIA TRANSMAXILAR | C51: 443.35 | E51: =D51*C51 -> 0
... A71: 030304004-1 | B71: Tratamento Clinico de Abscesso Cerebral | C71: 84.36 | E71: =D71*C71 -> 0
E72: =D72*C72 -> 0
E73: =D73*C73 -> 0
E74: =D74*C74 -> 0
E75: =D75*C75 -> 0
E76: =D76*C76 -> 0
E77: =D77*C77 -> 0
E78: =D78*C78 -> 0
E79: =D79*C79 -> 0
E80: =D80*C80 -> 0
E81: =D81*C81 -> 0
E82: =D82*C82 -> 0
E83: =D83*C83 -> 0
B84: Total | D84: =SUM(D13:D83) -> 0 | E84: =SUM(E13:E83) -> 0

Sheet CALCULOS EXTRAS
A5: 403010 | B5: 408030 | C5: 403020 | D5: 403030 | E5: 408040 | F5: 403050 | G5: OUTROS CODIGOS
A6: =COUNTIF('JULHO 2026'!E11:E603,'0403010'!A13)+COUNTIF('JULHO 2026'!E605:E1029,'0403010'!A13) -> 0 | B6: =COUNTIF('JULHO 2026'!E11:E603,'0408030'!A13)+COUNTIF('JULHO 2026'!E605:E1029,'0408030'!A13) -> 0 | C6: =COUNTIF('JULHO 2026'!E11:E603,'0403020'!A13)+COUNTIF('JULHO 2026'!E605:E1029,'0403020'!A13) -> 0 | D6: =COUNTIF('JULHO 2026'!E11:E603,'0403030'!A13)+COUNTIF('JULHO 2026'!E605:E1029,'0403030'!A13) -> 0 | E6: =COUNTIF('JULHO 2026'!E11:E603,'0403040'!A13)+COUNTIF('JULHO 2026'!E605:E1029,'0403040'!A13) -> 0 | F6: =COUNTIF('JULHO 2026'!E11:E603,'0403050'!A13)+COUNTIF('JULHO 2026'!E605:E1029,'0403050'!A13) -> 0 | G6: =COUNTIF('JULHO 2026'!E11:E603,'outros codigos'!A13)+COUNTIF('JULHO 2026'!E605:E1029,'outros codigos'!A13) -> 0 | J6: PROVA DE CALCULOS
A7: =COUNTIF('JULHO 2026'!E11:E603,'0403010'!A14)+COUNTIF('JULHO 2026'!E605:E1029,'0403010'!A14) -> 0 | B7: =COUNTIF('JULHO 2026'!E11:E603,'0408030'!A14)+COUNTIF('JULHO 2026'!E605:E1029,'0408030'!A14) -> 0 | C7: =COUNTIF('JULHO 2026'!E11:E603,'0403020'!A14)+COUNTIF('JULHO 2026'!E605:E1029,'0403020'!A14) -> 0 | D7: =COUNTIF('JULHO 2026'!E11:E603,'0403030'!A14)+COUNTIF('JULHO 2026'!E605:E1029,'0403030'!A14) -> 0 | E7: =COUNTIF('JULHO 2026'!E11:E603,'0403040'!A14)+COUNTIF('JULHO 2026'!E605:E1029,'0403040'!A14) -> 0 | F7: =COUNTIF('JULHO 2026'!E11:E603,'0403050'!A14)+COUNTIF('JULHO 2026'!E605:E1029,'0403050'!A14) -> 0 | G7: =COUNTIF('JULHO 2026'!E11:E603,'outros codigos'!A14)+COUNTIF('JULHO 2026'!E605:E1029,'outros codigos'!A14) -> 0 | I7: GERAL | J7: ='JULHO 2026'!G1034 -> 175954.42
A8: =COUNTIF('JULHO 2026'!E11:E603,'0403010'!A15)+COUNTIF('JULHO 2026'!E605:E1029,'0403010'!A15) -> 0 | B8: =COUNTIF('JULHO 2026'!E11:E603,'0408030'!A15)+COUNTIF('JULHO 2026'!E605:E1029,'0408030'!A15) -> 0 | C8: =COUNTIF('JULHO 2026'!E11:E603,'0403020'!A15)+COUNTIF('JULHO 2026'!E605:E1029,'0403020'!A15) -> 0 | D8: =COUNTIF('JULHO 2026'!E11:E603,'0403030'!A15)+COUNTIF('JULHO 2026'!E605:E1029,'0403030'!A15) -> 0 | E8: =COUNTIF('JULHO 2026'!E11:E603,'0403040'!A15)+COUNTIF('JULHO 2026'!E605:E1029,'0403040'!A15) -> 0 | F8: =COUNTIF('JULHO 2026'!E11:E603,'0403050'!A15)+COUNTIF('JULHO 2026'!E605:E1029,'0403050'!A15) -> 0 | G8: =COUNTIF('JULHO 2026'!E11:E603,'outros codigos'!A15)+COUNTIF('JULHO 2026'!E605:E1029,'outros codigos'!A15) -> 0 | I8: POR QUANTIDADE DE CODIGO | J8: =J19 -> 0
A9: =COUNTIF('JULHO 2026'!E11:E603,'0403010'!A16)+COUNTIF('JULHO 2026'!E605:E1029,'0403010'!A16) -> 0 | B9: =COUNTIF('JULHO 2026'!E11:E603,'0408030'!A16)+COUNTIF('JULHO 2026'!E605:E1029,'0408030'!A16) -> 0 | C9: =COUNTIF('JULHO 2026'!E11:E603,'0403020'!A16)+COUNTIF('JULHO 2026'!E605:E1029,'0403020'!A16) -> 0 | D9: =COUNTIF('JULHO 2026'!E11:E603,'0403030'!A16)+COUNTIF('JULHO 2026'!E605:E1029,'0403030'!A16) -> 0 | E9: =COUNTIF('JULHO 2026'!E11:E603,'0403040'!A16)+COUNTIF('JULHO 2026'!E605:E1029,'0403040'!A16) -> 0 | F9: =COUNTIF('JULHO 2026'!E11:E603,'0403050'!A16)+COUNTIF('JULHO 2026'!E605:E1029,'0403050'!A16) -> 0 | G9: =COUNTIF('JULHO 2026'!E11:E603,'outros codigos'!A16)+COUNTIF('JULHO 2026'!E605:E1029,'outros codigos'!A16) -> 0 | I9: MEDICOS | J9: ='por medico'!C28 -> 0
A10: =COUNTIF('JULHO 2026'!E11:E603,'0403010'!A17)+COUNTIF('JULHO 2026'!E605:E1029,'0403010'!A17) -> 0 | B10: =COUNTIF('JULHO 2026'!E11:E603,'0408030'!A17)+COUNTIF('JULHO 2026'!E605:E1029,'0408030'!A17) -> 0 | C10: =COUNTIF('JULHO 2026'!E11:E603,'0403020'!A17)+COUNTIF('JULHO 2026'!E605:E1029,'0403020'!A17) -> 0 | D10: =COUNTIF('JULHO 2026'!E11:E603,'0403030'!A17)+COUNTIF('JULHO 2026'!E605:E1029,'0403030'!A17) -> 0 | E10: =COUNTIF('JULHO 2026'!E11:E603,'0403040'!A17)+COUNTIF('JULHO 2026'!E605:E1029,'0403040'!A17) -> 0 | F10: =COUNTIF('JULHO 2026'!E11:E603,'0403050'!A17)+COUNTIF('JULHO 2026'!E605:E1029,'0403050'!A17) -> 0 | G10: =COUNTIF('JULHO 2026'!E11:E603,'outros codigos'!A17)+COUNTIF('JULHO 2026'!E605:E1029,'outros codigos'!A17) -> 0 | I10: Procedimento | J10: ='JULHO 2026'!E1032 -> 508
A11: =COUNTIF('JULHO 2026'!E11:E603,'0403010'!A18)+COUNTIF('JULHO 2026'!E605:E1029,'0403010'!A18) -> 0 | B11: =COUNTIF('JULHO 2026'!E11:E603,'0408030'!A18)+COUNTIF('JULHO 2026'!E605:E1029,'0408030'!A18) -> 0 | C11: =COUNTIF('JULHO 2026'!E11:E603,'0403020'!A18)+COUNTIF('JULHO 2026'!E605:E1029,'0403020'!A18) -> 0 | D11: =COUNTIF('JULHO 2026'!E11:E603,'0403030'!A18)+COUNTIF('JULHO 2026'!E605:E1029,'0403030'!A18) -> 0 | E11: =COUNTIF('JULHO 2026'!E11:E603,'0403040'!A18)+COUNTIF('JULHO 2026'!E605:E1029,'0403040'!A18) -> 0 | F11: =COUNTIF('JULHO 2026'!E11:E603,'0403050'!A18)+COUNTIF('JULHO 2026'!E605:E1029,'0403050'!A18) -> 0 | G11: =COUNTIF('JULHO 2026'!E11:E603,'outros codigos'!A18)+COUNTIF('JULHO 2026'!E605:E1029,'outros codigos'!A18) -> 0
A12: =COUNTIF('JULHO 2026'!E11:E603,'0403010'!A19)+COUNTIF('JULHO 2026'!E605:E1029,'0403010'!A19) -> 0 | B12: =COUNTIF('JULHO 2026'!E11:E603,'0408030'!A19)+COUNTIF('JULHO 2026'!E605:E1029,'0408030'!A19) -> 0 | C12: =COUNTIF('JULHO 2026'!E11:E603,'0403020'!A19)+COUNTIF('JULHO 2026'!E605:E1029,'0403020'!A19) -> 0 | D12: =COUNTIF('JULHO 2026'!E11:E603,'0403030'!A19)+COUNTIF('JULHO 2026'!E605:E1029,'0403030'!A19) -> 0 | E12: =COUNTIF('JULHO 2026'!E11:E603,'0403040'!A19)+COUNTIF('JULHO 2026'!E605:E1029,'0403040'!A19) -> 0 | F12: =COUNTIF('JULHO 2026'!E11:E603,'0403050'!A19)+COUNTIF('JULHO 2026'!E605:E1029,'0403050'!A19) -> 0 | G12: =COUNTIF('JULHO 2026'!E11:E603,'outros codigos'!A19)+COUNTIF('JULHO 2026'!E605:E1029,'outros codigos'!A19) -> 0 | J12: ='0403010'!E51 -> 0 | L12: ='0403010'!D51 -> 0
A13: =COUNTIF('JULHO 2026'!E11:E603,'0403010'!A20)+COUNTIF('JULHO 2026'!E605:E1029,'0403010'!A20) -> 0 | B13: =COUNTIF('JULHO 2026'!E11:E603,'0408030'!A20)+COUNTIF('JULHO 2026'!E605:E1029,'0408030'!A20) -> 0 | C13: =COUNTIF('JULHO 2026'!E11:E603,'0403020'!A20)+COUNTIF('JULHO 2026'!E605:E1029,'0403020'!A20) -> 0 | D13: =COUNTIF('JULHO 2026'!E11:E603,'0403030'!A20)+COUNTIF('JULHO 2026'!E605:E1029,'0403030'!A20) -> 0 | E13: =COUNTIF('JULHO 2026'!E11:E603,'0403040'!A20)+COUNTIF('JULHO 2026'!E605:E1029,'0403040'!A20) -> 0 | F13: =COUNTIF('JULHO 2026'!E11:E603,'0403050'!A20)+COUNTIF('JULHO 2026'!E605:E1029,'0403050'!A20) -> 0 | G13: =COUNTIF('JULHO 2026'!E11:E603,'outros codigos'!A20)+COUNTIF('JULHO 2026'!E605:E1029,'outros codigos'!A20) -> 0 | J13: ='0408030'!E105 -> 0 | L13: ='0408030'!D105 -> 0
A14: =COUNTIF('JULHO 2026'!E11:E603,'0403010'!A21)+COUNTIF('JULHO 2026'!E605:E1029,'0403010'!A21) -> 0 | B14: =COUNTIF('JULHO 2026'!E11:E603,'0408030'!A21)+COUNTIF('JULHO 2026'!E605:E1029,'0408030'!A21) -> 0 | C14: =COUNTIF('JULHO 2026'!E11:E603,'0403020'!A21)+COUNTIF('JULHO 2026'!E605:E1029,'0403020'!A21) -> 0 | D14: =COUNTIF('JULHO 2026'!E11:E603,'0403030'!A21)+COUNTIF('JULHO 2026'!E605:E1029,'0403030'!A21) -> 0 | E14: =COUNTIF('JULHO 2026'!E11:E603,'0403040'!A21)+COUNTIF('JULHO 2026'!E605:E1029,'0403040'!A21) -> 0 | F14: =COUNTIF('JULHO 2026'!E11:E603,'0403050'!A21)+COUNTIF('JULHO 2026'!E605:E1029,'0403050'!A21) -> 0 | G14: =COUNTIF('JULHO 2026'!E11:E603,'outros codigos'!A21)+COUNTIF('JULHO 2026'!E605:E1029,'outros codigos'!A21) -> 0 | J14: ='0403020'!E26 -> 0 | L14: ='0403020'!D26 -> 0
A15: =COUNTIF('JULHO 2026'!E11:E603,'0403010'!A22)+COUNTIF('JULHO 2026'!E605:E1029,'0403010'!A22) -> 0 | B15: =COUNTIF('JULHO 2026'!E11:E603,'0408030'!A22)+COUNTIF('JULHO 2026'!E605:E1029,'0408030'!A22) -> 0 | C15: =COUNTIF('JULHO 2026'!E11:E603,'0403020'!A22)+COUNTIF('JULHO 2026'!E605:E1029,'0403020'!A22) -> 0 | D15: =COUNTIF('JULHO 2026'!E11:E603,'0403030'!A22)+COUNTIF('JULHO 2026'!E605:E1029,'0403030'!A22) -> 0 | E15: =COUNTIF('JULHO 2026'!E11:E603,'0403040'!A22)+COUNTIF('JULHO 2026'!E605:E1029,'0403040'!A22) -> 0 | F15: =COUNTIF('JULHO 2026'!E11:E603,'0403050'!A22)+COUNTIF('JULHO 2026'!E605:E1029,'0403050'!A22) -> 0 | G15: =COUNTIF('JULHO 2026'!E11:E603,'outros codigos'!A22)+COUNTIF('JULHO 2026'!E605:E1029,'outros codigos'!A22) -> 0 | J15: ='0403030'!E28 -> 0 | L15: ='0403030'!D28 -> 0
A16: =COUNTIF('JULHO 2026'!E11:E603,'0403010'!A23)+COUNTIF('JULHO 2026'!E605:E1029,'0403010'!A23) -> 0 | B16: =COUNTIF('JULHO 2026'!E11:E603,'0408030'!A23)+COUNTIF('JULHO 2026'!E605:E1029,'0408030'!A23) -> 0 | C16: =COUNTIF('JULHO 2026'!E11:E603,'0403020'!A23)+COUNTIF('JULHO 2026'!E605:E1029,'0403020'!A23) -> 0 | D16: =COUNTIF('JULHO 2026'!E11:E603,'0403030'!A23)+COUNTIF('JULHO 2026'!E605:E1029,'0403030'!A23) -> 0 | F16: =COUNTIF('JULHO 2026'!E11:E603,'0403050'!A23)+COUNTIF('JULHO 2026'!E605:E1029,'0403050'!A23) -> 0 | G16: =COUNTIF('JULHO 2026'!E11:E603,'outros codigos'!A23)+COUNTIF('JULHO 2026'!E605:E1029,'outros codigos'!A23) -> 0 | J16: ='0403040'!E23 -> 0 | L16: ='0403040'!D23 -> 0
A17: =COUNTIF('JULHO 2026'!E11:E603,'0403010'!A24)+COUNTIF('JULHO 2026'!E605:E1029,'0403010'!A24) -> 0 | B17: =COUNTIF('JULHO 2026'!E11:E603,'0408030'!A24)+COUNTIF('JULHO 2026'!E605:E1029,'0408030'!A24) -> 0 | C17: =COUNTIF('JULHO 2026'!E11:E603,'0403020'!A24)+COUNTIF('JULHO 2026'!E605:E1029,'0403020'!A24) -> 0 | D17: =COUNTIF('JULHO 2026'!E11:E603,'0403030'!A24)+COUNTIF('JULHO 2026'!E605:E1029,'0403030'!A24) -> 0 | F17: =COUNTIF('JULHO 2026'!E11:E603,'0403050'!A24)+COUNTIF('JULHO 2026'!E605:E1029,'0403050'!A24) -> 0 | G17: =COUNTIF('JULHO 2026'!E11:E603,'outros codigos'!A24)+COUNTIF('JULHO 2026'!E605:E1029,'outros codigos'!A24) -> 0 | J17: ='0403050'!E29 -> 0 | L17: ='0403050'!D29 -> 0
A18: =COUNTIF('JULHO 2026'!E11:E603,'0403010'!A25)+COUNTIF('JULHO 2026'!E605:E1029,'0403010'!A25) -> 0 | B18: =COUNTIF('JULHO 2026'!E11:E603,'0408030'!A25)+COUNTIF('JULHO 2026'!E605:E1029,'0408030'!A25) -> 0 | C18: =COUNTIF('JULHO 2026'!E11:E603,'0403020'!A25)+COUNTIF('JULHO 2026'!E605:E1029,'0403020'!A25) -> 0 | D18: =COUNTIF('JULHO 2026'!E11:E603,'0403030'!A25)+COUNTIF('JULHO 2026'!E605:E1029,'0403030'!A25) -> 0 | F18: =COUNTIF('JULHO 2026'!E11:E603,'0403050'!A25)+COUNTIF('JULHO 2026'!E605:E1029,'0403050'!A25) -> 0 | G18: =COUNTIF('JULHO 2026'!E11:E603,'outros codigos'!A25)+COUNTIF('JULHO 2026'!E605:E1029,'outros codigos'!A25) -> 0 | J18: ='outros codigos'!E84 -> 0 | L18: ='outros codigos'!D84 -> 0
A19: =COUNTIF('JULHO 2026'!E11:E603,'0403010'!A26)+COUNTIF('JULHO 2026'!E605:E1029,'0403010'!A26) -> 0 | B19: =COUNTIF('JULHO 2026'!E11:E603,'0408030'!A26)+COUNTIF('JULHO 2026'!E605:E1029,'0408030'!A26) -> 0 | D19: =COUNTIF('JULHO 2026'!E11:E603,'0403030'!A26)+COUNTIF('JULHO 2026'!E605:E1029,'0403030'!A26) -> 0 | F19: =COUNTIF('JULHO 2026'!E11:E603,'0403050'!A26)+COUNTIF('JULHO 2026'!E605:E1029,'0403050'!A26) -> 0 | G19: =COUNTIF('JULHO 2026'!E11:E603,'outros codigos'!A26)+COUNTIF('JULHO 2026'!E605:E1029,'outros codigos'!A26) -> 0 | J19: =SUM(J12:J18) -> 0 | L19: =SUM(L12:L18) -> 0
A20: =COUNTIF('JULHO 2026'!E11:E603,'0403010'!A27)+COUNTIF('JULHO 2026'!E605:E1029,'0403010'!A27) -> 0 | B20: =COUNTIF('JULHO 2026'!E11:E603,'0408030'!A27)+COUNTIF('JULHO 2026'!E605:E1029,'0408030'!A27) -> 0 | D20: =COUNTIF('JULHO 2026'!E11:E603,'0403030'!A27)+COUNTIF('JULHO 2026'!E605:E1029,'0403030'!A27) -> 0 | F20: =COUNTIF('JULHO 2026'!E11:E603,'0403050'!A27)+COUNTIF('JULHO 2026'!E605:E1029,'0403050'!A27) -> 0 | G20: =COUNTIF('JULHO 2026'!E11:E603,'outros codigos'!A27)+COUNTIF('JULHO 2026'!E605:E1029,'outros codigos'!A27) -> 0
A21: =COUNTIF('JULHO 2026'!E11:E603,'0403010'!A28)+COUNTIF('JULHO 2026'!E605:E1029,'0403010'!A28) -> 0 | B21: =COUNTIF('JULHO 2026'!E11:E603,'0408030'!A28)+COUNTIF('JULHO 2026'!E605:E1029,'0408030'!A28) -> 0 | F21: =COUNTIF('JULHO 2026'!E11:E603,'0403050'!A28)+COUNTIF('JULHO 2026'!E605:E1029,'0403050'!A28) -> 0 | G21: =COUNTIF('JULHO 2026'!E11:E603,'outros codigos'!A28)+COUNTIF('JULHO 2026'!E605:E1029,'outros codigos'!A28) -> 0
A22: =COUNTIF('JULHO 2026'!E11:E603,'0403010'!A29)+COUNTIF('JULHO 2026'!E605:E1029,'0403010'!A29) -> 0 | B22: =COUNTIF('JULHO 2026'!E11:E603,'0408030'!A29)+COUNTIF('JULHO 2026'!E605:E1029,'0408030'!A29) -> 0 | G22: =COUNTIF('JULHO 2026'!E11:E603,'outros codigos'!A29)+COUNTIF('JULHO 2026'!E605:E1029,'outros codigos'!A29) -> 0 | J22: =J8-J9 -> 0
A23: =COUNTIF('JULHO 2026'!E11:E603,'0403010'!A30)+COUNTIF('JULHO 2026'!E605:E1029,'0403010'!A30) -> 0 | B23: =COUNTIF('JULHO 2026'!E11:E603,'0408030'!A30)+COUNTIF('JULHO 2026'!E605:E1029,'0408030'!A30) -> 0
A24: =COUNTIF('JULHO 2026'!E11:E603,'0403010'!A31)+COUNTIF('JULHO 2026'!E605:E1029,'0403010'!A31) -> 0 | B24: =COUNTIF('JULHO 2026'!E11:E603,'0408030'!A31)+COUNTIF('JULHO 2026'!E605:E1029,'0408030'!A31) -> 0
A25: =COUNTIF('JULHO 2026'!E11:E603,'0403010'!A32)+COUNTIF('JULHO 2026'!E605:E1029,'0403010'!A32) -> 0 | B25: =COUNTIF('JULHO 2026'!E11:E603,'0408030'!A32)+COUNTIF('JULHO 2026'!E605:E1029,'0408030'!A32) -> 0
A26: =COUNTIF('JULHO 2026'!E11:E603,'0403010'!A33)+COUNTIF('JULHO 2026'!E605:E1029,'0403010'!A33) -> 0 | B26: =COUNTIF('JULHO 2026'!E11:E603,'0408030'!A33)+COUNTIF('JULHO 2026'!E605:E1029,'0408030'!A33) -> 0
A27: =COUNTIF('JULHO 2026'!E11:E603,'0403010'!A34)+COUNTIF('JULHO 2026'!E605:E1029,'0403010'!A34) -> 0 | B27: =COUNTIF('JULHO 2026'!E11:E603,'0408030'!A34)+COUNTIF('JULHO 2026'!E605:E1029,'0408030'!A34) -> 0
A28: =COUNTIF('JULHO 2026'!E11:E603,'0403010'!A35)+COUNTIF('JULHO 2026'!E605:E1029,'0403010'!A35) -> 0 | B28: =COUNTIF('JULHO 2026'!E11:E603,'0408030'!A35)+COUNTIF('JULHO 2026'!E605:E1029,'0408030'!A35) -> 0
A29: =COUNTIF('JULHO 2026'!E11:E603,'0403010'!A37)+COUNTIF('JULHO 2026'!E605:E1029,'0403010'!A37) -> 0 | B29: =COUNTIF('JULHO 2026'!E11:E603,'0408030'!A36)+COUNTIF('JULHO 2026'!E605:E1029,'0408030'!A36) -> 0
A30: =COUNTIF('JULHO 2026'!E11:E603,'0403010'!A38)+COUNTIF('JULHO 2026'!E605:E1029,'0403010'!A38) -> 0 | B30: =COUNTIF('JULHO 2026'!E11:E603,'0408030'!A37)+COUNTIF('JULHO 2026'!E605:E1029,'0408030'!A37) -> 0
A31: =COUNTIF('JULHO 2026'!E11:E603,'0403010'!A39)+COUNTIF('JULHO 2026'!E605:E1029,'0403010'!A39) -> 0 | B31: =COUNTIF('JULHO 2026'!E11:E603,'0408030'!A38)+COUNTIF('JULHO 2026'!E605:E1029,'0408030'!A38) -> 0
A32: =COUNTIF('JULHO 2026'!E11:E603,'0403010'!A40)+COUNTIF('JULHO 2026'!E605:E1029,'0403010'!A40) -> 0 | B32: =COUNTIF('JULHO 2026'!E11:E603,'0408030'!A40)+COUNTIF('JULHO 2026'!E605:E1029,'0408030'!A40) -> 0
A33: =COUNTIF('JULHO 2026'!E11:E603,'0403010'!A41)+COUNTIF('JULHO 2026'!E605:E1029,'0403010'!A41) -> 0 | B33: =COUNTIF('JULHO 2026'!E11:E603,'0408030'!A41)+COUNTIF('JULHO 2026'!E605:E1029,'0408030'!A41) -> 0
A34: =COUNTIF('JULHO 2026'!E11:E603,'0403010'!A42)+COUNTIF('JULHO 2026'!E605:E1029,'0403010'!A42) -> 0 | B34: =COUNTIF('JULHO 2026'!E11:E603,'0408030'!A42)+COUNTIF('JULHO 2026'!E605:E1029,'0408030'!A42) -> 0
A35: =COUNTIF('JULHO 2026'!E11:E603,'0403010'!A43)+COUNTIF('JULHO 2026'!E605:E1029,'0403010'!A43) -> 0 | B35: =COUNTIF('JULHO 2026'!E11:E603,'0408030'!A43)+COUNTIF('JULHO 2026'!E605:E1029,'0408030'!A43) -> 0
A36: =COUNTIF('JULHO 2026'!E11:E603,'0403010'!A44)+COUNTIF('JULHO 2026'!E605:E1029,'0403010'!A44) -> 0 | B36: =COUNTIF('JULHO 2026'!E11:E603,'0408030'!A44)+COUNTIF('JULHO 2026'!E605:E1029,'0408030'!A44) -> 0
A37: =COUNTIF('JULHO 2026'!E11:E603,'0403010'!A45)+COUNTIF('JULHO 2026'!E605:E1029,'0403010'!A45) -> 0 | B37: =COUNTIF('JULHO 2026'!E11:E603,'0408030'!A45)+COUNTIF('JULHO 2026'!E605:E1029,'0408030'!A45) -> 0
A38: =COUNTIF('JULHO 2026'!E11:E603,'0403010'!A46)+COUNTIF('JULHO 2026'!E605:E1029,'0403010'!A46) -> 0 | B38: =COUNTIF('JULHO 2026'!E11:E603,'0408030'!A46)+COUNTIF('JULHO 2026'!E605:E1029,'0408030'!A46) -> 0
A39: =COUNTIF('JULHO 2026'!E11:E603,'0403010'!A47)+COUNTIF('JULHO 2026'!E605:E1029,'0403010'!A47) -> 0 | B39: =COUNTIF('JULHO 2026'!E11:E603,'0408030'!A47)+COUNTIF('JULHO 2026'!E605:E1029,'0408030'!A47) -> 0
A40: =COUNTIF('JULHO 2026'!E11:E603,'0403010'!A48)+COUNTIF('JULHO 2026'!E605:E1029,'0403010'!A48) -> 0 | B40: =COUNTIF('JULHO 2026'!E11:E603,'0408030'!A48)+COUNTIF('JULHO 2026'!E605:E1029,'0408030'!A48) -> 0
A41: =COUNTIF('JULHO 2026'!E11:E603,'0403010'!A49)+COUNTIF('JULHO 2026'!E605:E1029,'0403010'!A49) -> 0 | B41: =COUNTIF('JULHO 2026'!E11:E603,'0408030'!A49)+COUNTIF('JULHO 2026'!E605:E1029,'0408030'!A49) -> 0
A42: =COUNTIF('JULHO 2026'!E11:E603,'0403010'!A50)+COUNTIF('JULHO 2026'!E605:E1029,'0403010'!A50) -> 0 | B42: =COUNTIF('JULHO 2026'!E11:E603,'0408030'!A50)+COUNTIF('JULHO 2026'!E605:E1029,'0408030'!A50) -> 0
B43: =COUNTIF('JULHO 2026'!E11:E603,'0408030'!A51)+COUNTIF('JULHO 2026'!E605:E1029,'0408030'!A51) -> 0
B44: =COUNTIF('JULHO 2026'!E11:E603,'0408030'!A52)+COUNTIF('JULHO 2026'!E605:E1029,'0408030'!A52) -> 0
B45: =COUNTIF('JULHO 2026'!E11:E603,'0408030'!A53)+COUNTIF('JULHO 2026'!E605:E1029,'0408030'!A53) -> 0
B46: =COUNTIF('JULHO 2026'!E11:E603,'0408030'!A54)+COUNTIF('JULHO 2026'!E605:E1029,'0408030'!A54) -> 0
B47: =COUNTIF('JULHO 2026'!E11:E603,'0408030'!A55)+COUNTIF('JULHO 2026'!E605:E1029,'0408030'!A55) -> 0
B48: =COUNTIF('JULHO 2026'!E11:E603,'0408030'!A56)+COUNTIF('JULHO 2026'!E605:E1029,'0408030'!A56) -> 0
B49: =COUNTIF('JULHO 2026'!E11:E603,'0408030'!A57)+COUNTIF('JULHO 2026'!E605:E1029,'0408030'!A57) -> 0
B50: =COUNTIF('JULHO 2026'!E11:E603,'0408030'!A58)+COUNTIF('JULHO 2026'!E605:E1029,'0408030'!A58) -> 0
B51: =COUNTIF('JULHO 2026'!E11:E603,'0408030'!A59)+COUNTIF('JULHO 2026'!E605:E1029,'0408030'!A59) -> 0
B52: =COUNTIF('JULHO 2026'!E11:E603,'0408030'!A60)+COUNTIF('JULHO 2026'!E605:E1029,'0408030'!A60) -> 0
B53: =COUNTIF('JULHO 2026'!E11:E603,'0408030'!A61)+COUNTIF('JULHO 2026'!E605:E1029,'0408030'!A61) -> 0
B54: =COUNTIF('JULHO 2026'!E11:E603,'0408030'!A62)+COUNTIF('JULHO 2026'!E605:E1029,'0408030'!A62) -> 0
B55: =COUNTIF('JULHO 2026'!E11:E603,'0408030'!A63)+COUNTIF('JULHO 2026'!E605:E1029,'0408030'!A63) -> 0
B56: =COUNTIF('JULHO 2026'!E11:E603,'0408030'!A64)+COUNTIF('JULHO 2026'!E605:E1029,'0408030'!A64) -> 0
B57: =COUNTIF('JULHO 2026'!E11:E603,'0408030'!A65)+COUNTIF('JULHO 2026'!E605:E1029,'0408030'!A65) -> 0
B58: =COUNTIF('JULHO 2026'!E11:E603,'0408030'!A66)+COUNTIF('JULHO 2026'!E605:E1029,'0408030'!A66) -> 0
B59: =COUNTIF('JULHO 2026'!E11:E603,'0408030'!A67)+COUNTIF('JULHO 2026'!E605:E1029,'0408030'!A67) -> 0
B60: =COUNTIF('JULHO 2026'!E11:E603,'0408030'!A68)+COUNTIF('JULHO 2026'!E605:E1029,'0408030'!A68) -> 0
B61: =COUNTIF('JULHO 2026'!E11:E603,'0408030'!A69)+COUNTIF('JULHO 2026'!E605:E1029,'0408030'!A69) -> 0
B62: =COUNTIF('JULHO 2026'!E11:E603,'0408030'!A70)+COUNTIF('JULHO 2026'!E605:E1029,'0408030'!A70) -> 0
B63: =COUNTIF('JULHO 2026'!E11:E603,'0408030'!A71)+COUNTIF('JULHO 2026'!E605:E1029,'0408030'!A71) -> 0
B64: =COUNTIF('JULHO 2026'!E11:E603,'0408030'!A72)+COUNTIF('JULHO 2026'!E605:E1029,'0408030'!A72) -> 0
B65: =COUNTIF('JULHO 2026'!E11:E603,'0408030'!A73)+COUNTIF('JULHO 2026'!E605:E1029,'0408030'!A73) -> 0
B66: =COUNTIF('JULHO 2026'!E11:E603,'0408030'!A74)+COUNTIF('JULHO 2026'!E605:E1029,'0408030'!A74) -> 0
B67: =COUNTIF('JULHO 2026'!E11:E603,'0408030'!A75)+COUNTIF('JULHO 2026'!E605:E1029,'0408030'!A75) -> 0
B68: =COUNTIF('JULHO 2026'!E11:E603,'0408030'!A76)+COUNTIF('JULHO 2026'!E605:E1029,'0408030'!A76) -> 0
B69: =COUNTIF('JULHO 2026'!E11:E603,'0408030'!A78)+COUNTIF('JULHO 2026'!E605:E1029,'0408030'!A78) -> 0
B70: =COUNTIF('JULHO 2026'!E11:E603,'0408030'!A79)+COUNTIF('JULHO 2026'!E605:E1029,'0408030'!A79) -> 0
B71: =COUNTIF('JULHO 2026'!E11:E603,'0408030'!A80)+COUNTIF('JULHO 2026'!E605:E1029,'0408030'!A80) -> 0
B72: =COUNTIF('JULHO 2026'!E11:E603,'0408030'!A81)+COUNTIF('JULHO 2026'!E605:E1029,'0408030'!A81) -> 0
B73: =COUNTIF('JULHO 2026'!E11:E603,'0408030'!A82)+COUNTIF('JULHO 2026'!E605:E1029,'0408030'!A82) -> 0
B74: =COUNTIF('JULHO 2026'!E11:E603,'0408030'!A83)+COUNTIF('JULHO 2026'!E605:E1029,'0408030'!A83) -> 0
B75: =COUNTIF('JULHO 2026'!E11:E603,'0408030'!A84)+COUNTIF('JULHO 2026'!E605:E1029,'0408030'!A84) -> 0
B76: =COUNTIF('JULHO 2026'!E11:E603,'0408030'!A85)+COUNTIF('JULHO 2026'!E605:E1029,'0408030'!A85) -> 0
B77: =COUNTIF('JULHO 2026'!E11:E603,'0408030'!A86)+COUNTIF('JULHO 2026'!E605:E1029,'0408030'!A86) -> 0
B78: =COUNTIF('JULHO 2026'!E11:E603,'0408030'!A87)+COUNTIF('JULHO 2026'!E605:E1029,'0408030'!A87) -> 0
B79: =COUNTIF('JULHO 2026'!E11:E603,'0408030'!A88)+COUNTIF('JULHO 2026'!E605:E1029,'0408030'!A88) -> 0
B80: =COUNTIF('JULHO 2026'!E11:E603,'0408030'!A89)+COUNTIF('JULHO 2026'!E605:E1029,'0408030'!A89) -> 0
B81: =COUNTIF('JULHO 2026'!E11:E603,'0408030'!A90)+COUNTIF('JULHO 2026'!E605:E1029,'0408030'!A90) -> 0
B82: =COUNTIF('JULHO 2026'!E11:E603,'0408030'!A91)+COUNTIF('JULHO 2026'!E605:E1029,'0408030'!A91) -> 0
B83: =COUNTIF('JULHO 2026'!E11:E603,'0408030'!A92)+COUNTIF('JULHO 2026'!E605:E1029,'0408030'!A92) -> 0
B84: =COUNTIF('JULHO 2026'!E11:E603,'0408030'!A93)+COUNTIF('JULHO 2026'!E605:E1029,'0408030'!A93) -> 0
B85: =COUNTIF('JULHO 2026'!E11:E603,'0408030'!A94)+COUNTIF('JULHO 2026'!E605:E1029,'0408030'!A94) -> 0
B86: =COUNTIF('JULHO 2026'!E11:E603,'0408030'!A95)+COUNTIF('JULHO 2026'!E605:E1029,'0408030'!A95) -> 0
B87: =COUNTIF('JULHO 2026'!E11:E603,'0408030'!A96)+COUNTIF('JULHO 2026'!E605:E1029,'0408030'!A96) -> 0
B88: =COUNTIF('JULHO 2026'!E11:E603,'0408030'!A97)+COUNTIF('JULHO 2026'!E605:E1029,'0408030'!A97) -> 0
B89: =COUNTIF('JULHO 2026'!E11:E603,'0408030'!A98)+COUNTIF('JULHO 2026'!E605:E1029,'0408030'!A98) -> 0
B90: =COUNTIF('JULHO 2026'!E11:E603,'0408030'!A99)+COUNTIF('JULHO 2026'!E605:E1029,'0408030'!A99) -> 0
B91: =COUNTIF('JULHO 2026'!E11:E603,'0408030'!A100)+COUNTIF('JULHO 2026'!E605:E1029,'0408030'!A100) -> 0
B92: =COUNTIF('JULHO 2026'!E11:E603,'0408030'!A101)+COUNTIF('JULHO 2026'!E605:E1029,'0408030'!A101) -> 0
B93: =COUNTIF('JULHO 2026'!E11:E603,'0408030'!A102)+COUNTIF('JULHO 2026'!E605:E1029,'0408030'!A102) -> 0
B94: =COUNTIF('JULHO 2026'!E11:E603,'0408030'!A103)+COUNTIF('JULHO 2026'!E605:E1029,'0408030'!A103) -> 0
B95: =COUNTIF('JULHO 2026'!E11:E603,'0408030'!A104)+COUNTIF('JULHO 2026'!E605:E1029,'0408030'!A104) -> 0

Sheet PENDENCIAS
D6: PENDENCIAS JULHO 2026 | E6: 46251
D7: NEUROCIRUGIA
A9: 1 | B9: 46209 | C9: 20302022 | D9: UBIRAJARA RODRIGUES DE CARVALHO | E9: WAGNER HERCULANO
A10: 2 | B10: 46220 | C10: 20398822 | D10: ELINEUZA CERQUIRA DA SILVA | E10: LUIZ SOEIRO | F10: **teve cirurgia tb no dia 09/07 já ok
A11: 3 | B11: 46223 | C11: 14749915 | D11: RICARDO BRAGA VIANA | E11: WAGNER HERCULANO
A12: 4 | B12: 46227 | C12: 15105216 | D12: ANGELO MARCIO DOS SNTOS LIMA | E12: WAGNER HERCULANO | F12: **teve cirurgia tb no dia 11/07 já ok
A13: 5 | B13: 46230 | C13: 20355533 | D13: SIMONE DA SILVA | E13: WAGNER HERCULANO
A14: 6 | B14: 46231 | C14: 20662961 | D14: MARIA ZULEIDE DOS SANTOS NASCIMENTO | E14: CAMILA MOURA | J14: 13
A15: 7 | B15: 46233 | C15: 6004071 | D15: CELIA MARIA PINTO DA SILVA | E15: WAGNER HERCULANO | J15: 11
J16: 12
J17: 13
J18: 13
J19: 13
J20: 12
D34: PENDENCIAS MAIO 2026 | E34: 46191
D35: NEUROCIRUGIA
A37: 1 | B37: 46143 | C37: 10714434 | D37: JUCINEY BARBOSA NDOS SANTOS | E37: LUIZ SOEIRO
A38: 2 | B38: 46148 | C38: 17472911 | D38: CIRENIO RODRIGUES DE SOUZA | E38: EDUARDO VARJÃO
A39: 3 | B39: 46158 | C39: 19178870 | D39: MARCELO PEREIRA DA SILVA | E39: IOGO HENRIQUE
A40: 4 | B40: 46159 | C40: 19460773 | D40: TEREZINHA JESUS DE LIMA | E40: EDUARDO VARJÃO
A41: 5 | B41: 46160 | C41: 18896357 | D41: WELINGTON SIMOES LIMA | E41: WAGNER HERCULANO
A42: 6 | B42: 46172 | C42: 15437825 | D42: MARIA FELICIA PEREIRA FIAES | E42: IOGO HENRIQUE
D49: PENDENCIAS MAIO 2026 | E49: 46190
D50: NEUROCIRUGIA
A52: 1 | B52: 46143 | C52: 10714434 | D52: JUCINEY BARBOSA NDOS SANTOS | E52: LUIZ SOEIRO
A53: 2 | B53: 46148 | C53: 17472911 | D53: CIRENIO RODRIGUES DE SOUZA | E53: EDUARDO VARJÃO
A54: 3 | B54: 46157 | E54: WAGNER HERCULANO
A55: 4 | B55: 46157 | E55: WAGNER HERCULANO
A56: 5 | B56: 46158 | C56: 19178870 | D56: MARCELO PEREIRA DA SILVA | E56: IOGO HENRIQUE
A57: 6 | B57: 46159 | C57: 19460773 | D57: TEREZINHA JESUS DE LIMA | E57: EDUARDO VARJÃO
A58: 7 | B58: 46160 | C58: 18896357 | D58: WELINGTON SIMOES LIMA | E58: WAGNER HERCULANO
A59: 8 | B59: 46162 | E59: WAGNER HERCULANO
A60: 9 | B60: 46164 | E60: LUIZ SOEIRO
A61: 10 | B61: 46168 | E61: PEDRO HENRIQUE
A62: 11 | B62: 46169 | E62: JAQUISSON GUIMARÃES
A63: 12 | B63: 46170 | E63: WAGNER HERCULANO
A64: 13 | B64: 46172 | C64: 15437825 | D64: MARIA FELICIA PEREIRA FIAES | E64: IOGO HENRIQUE
A65: 14 | B65: 30/052026 | E65: IOGO HENRIQUE
A66: 15 | B66: 31/052026 | C66: 13469093 | D66: MARIA DE LOURDES MATOS DE JESUS | E66: WAGNER HERCULANO

Sheet OBSERVAÇÕES
D9: OPME
D10: CL da dor
N33: 9
N34: 10
N35: 10
N36: 10
N37: 8
N38: 9
N39: 9
N40: 9
N41: 10
N42: 9
N43: 8
N44: 6

Sheet Planilha1

Sheet POR PACIENTE
A1: GOVERNO DO ESTADO DA BAHIA
A2: Secretaria da Saúde do Estado da Bahia – SESAB
A3: Hospital Geral Clériston Andrade - HGCA
A6: De: Contas Hospitalares
A7: Para: Diretoria Médica/ Coordenação Neurologia
A9: Relatório de Pacientes que realizaram neurocirurgia no HGCA
A10: DATA:
A13: PACIENTE | B13: frequencia mensal | C13: Valor pago
A14: ='JULHO 2026'!D11 -> 19999507 | B14: =COUNTIF('JULHO 2026'!D11:D599,'POR PACIENTE'!A10) -> 0
A15: ='JULHO 2026'!D17 -> 20170007 | B15: =COUNTIF('JULHO 2026'!D11:D599,'POR PACIENTE'!A16) -> 1
A16: ='JULHO 2026'!D23 -> 18270306 | B16: =COUNTIF('JULHO 2026'!D11:D599,'POR PACIENTE'!A22) -> 1
A17: ='JULHO 2026'!D29 -> 16019804 | B17: =COUNTIF('JULHO 2026'!D11:D599,'POR PACIENTE'!A28) -> 1
A18: ='JULHO 2026'!D35 -> 20207494 | B18: =COUNTIF('JULHO 2026'!D11:D599,'POR PACIENTE'!A34) -> 1
A19: ='JULHO 2026'!D41 -> 20207510 | B19: =COUNTIF('JULHO 2026'!D11:D599,'POR PACIENTE'!A40) -> 1
A20: ='JULHO 2026'!D47 -> 19937804 | B20: =COUNTIF('JULHO 2026'!D11:D599,'POR PACIENTE'!A46) -> 1
A21: ='JULHO 2026'!D53 -> 14123228 | B21: =COUNTIF('JULHO 2026'!D11:D599,'POR PACIENTE'!A53) -> 1
A22: ='JULHO 2026'!D59 -> 20051595 | B22: =COUNTIF('JULHO 2026'!D11:D599,'POR PACIENTE'!A59) -> 1
A23: ='JULHO 2026'!D65 -> 20166112 | B23: =COUNTIF('JULHO 2026'!D11:D599,'POR PACIENTE'!A65) -> 1
A24: ='JULHO 2026'!D71 -> 15673171 | B24: =COUNTIF('JULHO 2026'!D11:D599,'POR PACIENTE'!A71) -> 1
A25: ='JULHO 2026'!D77 -> 10477966 | B25: =COUNTIF('JULHO 2026'!D11:D599,'POR PACIENTE'!A77) -> 1
A26: ='JULHO 2026'!D83 -> 10274421 | B26: =COUNTIF('JULHO 2026'!D11:D599,'POR PACIENTE'!A83) -> 1
A27: ='JULHO 2026'!D89 -> 20319273 | B27: =COUNTIF('JULHO 2026'!D11:D599,'POR PACIENTE'!A89) -> 1
A28: ='JULHO 2026'!D95 -> 20275442 | B28: =COUNTIF('JULHO 2026'!D11:D599,'POR PACIENTE'!A95) -> 1
A29: ='JULHO 2026'!D101 -> 4234761 | B29: =COUNTIF('JULHO 2026'!D11:D599,'POR PACIENTE'!A102) -> 0
A30: ='JULHO 2026'!D107 -> 29297966 | B30: =COUNTIF('JULHO 2026'!D11:D599,'POR PACIENTE'!A108) -> 0
A31: ='JULHO 2026'!D113 -> 20329637 | B31: =COUNTIF('JULHO 2026'!D11:D599,'POR PACIENTE'!A114) -> 0
A32: ='JULHO 2026'!D119 -> 20313573 | B32: =COUNTIF('JULHO 2026'!D11:D599,'POR PACIENTE'!A120) -> 0
A33: ='JULHO 2026'!D125 -> 20338463 | B33: =COUNTIF('JULHO 2026'!D11:D599,'POR PACIENTE'!A126) -> 0
A34: ='JULHO 2026'!D131 -> 18069914 | B34: =COUNTIF('JULHO 2026'!D11:D599,'POR PACIENTE'!A132) -> 0
A35: ='JULHO 2026'!D137 -> 20428447 | B35: =COUNTIF('JULHO 2026'!D11:D599,'POR PACIENTE'!A138) -> 0
A36: ='JULHO 2026'!D143 -> 20405965 | B36: =COUNTIF('JULHO 2026'!D11:D599,'POR PACIENTE'!A144) -> 0
A37: ='JULHO 2026'!D149 -> 19892868 | B37: =COUNTIF('JULHO 2026'!D11:D599,'POR PACIENTE'!A150) -> 0
A38: ='JULHO 2026'!D155 -> 20261186 | B38: =COUNTIF('JULHO 2026'!D11:D599,'POR PACIENTE'!A156) -> 0
A39: ='JULHO 2026'!D161 -> 20385191 | B39: =COUNTIF('JULHO 2026'!D11:D599,'POR PACIENTE'!A162) -> 0
A40: ='JULHO 2026'!D167 -> 20405734 | B40: =COUNTIF('JULHO 2026'!D11:D599,'POR PACIENTE'!A168) -> 0
A41: ='JULHO 2026'!D173 -> 20316758 | B41: =COUNTIF('JULHO 2026'!D11:D599,'POR PACIENTE'!A174) -> 0
A42: ='JULHO 2026'!D179 -> 20441002 | B42: =COUNTIF('JULHO 2026'!D11:D599,'POR PACIENTE'!A180) -> 0
A43: ='JULHO 2026'!D185 -> 20118261 | B43: =COUNTIF('JULHO 2026'!D11:D599,'POR PACIENTE'!A186) -> 0
A44: ='JULHO 2026'!D191 -> 20398822 | B44: =COUNTIF('JULHO 2026'!D11:D599,'POR PACIENTE'!A192) -> 0
A45: ='JULHO 2026'!D197 -> 20426466 | B45: =COUNTIF('JULHO 2026'!D11:D599,'POR PACIENTE'!A198) -> 0
A46: ='JULHO 2026'!D203 -> 20416632 | B46: =COUNTIF('JULHO 2026'!D11:D599,'POR PACIENTE'!A204) -> 0
A47: ='JULHO 2026'!D209 -> 20530143 | B47: =COUNTIF('JULHO 2026'!D11:D599,'POR PACIENTE'!A210) -> 0
A48: ='JULHO 2026'!D215 -> 20186698 | B48: =COUNTIF('JULHO 2026'!D11:D599,'POR PACIENTE'!A216) -> 0
A49: ='JULHO 2026'!D221 -> 20424636 | B49: =COUNTIF('JULHO 2026'!D11:D599,'POR PACIENTE'!A222) -> 0
A50: PACIENTE | B50: frequencia mensal | C50: Valor pago
A51: ='JULHO 2026'!D227 -> 20324711 | B51: =COUNTIF('JULHO 2026'!D11:D599,'POR PACIENTE'!A228) -> 0
A52: ='JULHO 2026'!D233 -> 20665766 | B52: =COUNTIF('JULHO 2026'!D11:D599,'POR PACIENTE'!A234) -> 0
A53: ='JULHO 2026'!D239 -> 20765954 | B53: =COUNTIF('JULHO 2026'!D11:D599,'POR PACIENTE'!A240) -> 0
A54: ='JULHO 2026'!D245 -> 20723219 | B54: =COUNTIF('JULHO 2026'!D11:D599,'POR PACIENTE'!A246) -> 0
A55: ='JULHO 2026'!D251 -> 18965277 | B55: =COUNTIF('JULHO 2026'!D11:D599,'POR PACIENTE'!A252) -> 0
A56: ='JULHO 2026'!D257 -> 14457824 | B56: =COUNTIF('JULHO 2026'!D11:D599,'POR PACIENTE'!A258) -> 0
A57: ='JULHO 2026'!D269 -> 20417739 | B57: =COUNTIF('JULHO 2026'!D11:D599,'POR PACIENTE'!A264) -> 0
A58: ='JULHO 2026'!D269 -> 20417739 | B58: =COUNTIF('JULHO 2026'!D11:D599,'POR PACIENTE'!A270) -> 0
A59: ='JULHO 2026'!D275 -> 20599759 | B59: =COUNTIF('JULHO 2026'!D11:D599,'POR PACIENTE'!A276) -> 0
A60: ='JULHO 2026'!D281 -> 20482220 | B60: =COUNTIF('JULHO 2026'!D11:D599,'POR PACIENTE'!A282) -> 0
A61: ='JULHO 2026'!D287 -> 16688154 | B61: =COUNTIF('JULHO 2026'!D11:D599,'POR PACIENTE'!A288) -> 0
A62: ='JULHO 2026'!D293 -> 9525684 | B62: =COUNTIF('JULHO 2026'!D11:D599,'POR PACIENTE'!A294) -> 0
A63: ='JULHO 2026'!D299 -> 20497293 | B63: =COUNTIF('JULHO 2026'!D11:D599,'POR PACIENTE'!A300) -> 0
A64: ='JULHO 2026'!D305 -> 20497293 | B64: =COUNTIF('JULHO 2026'!D11:D599,'POR PACIENTE'!A306) -> 0
A65: ='JULHO 2026'!D311 -> 20692646 | B65: =COUNTIF('JULHO 2026'!D11:D599,'POR PACIENTE'!A312) -> 0
A66: ='JULHO 2026'!D317 -> 20740593 | B66: =COUNTIF('JULHO 2026'!D11:D599,'POR PACIENTE'!A318) -> 0
A67: ='JULHO 2026'!D323 -> 20722633 | B67: =COUNTIF('JULHO 2026'!D11:D599,'POR PACIENTE'!A324) -> 0
A68: ='JULHO 2026'!D329 -> 10274421 | B68: =COUNTIF('JULHO 2026'!D11:D599,'POR PACIENTE'!A330) -> 0
A69: ='JULHO 2026'!D335 -> 20554051 | B69: =COUNTIF('JULHO 2026'!D11:D599,'POR PACIENTE'!A336) -> 0
A70: ='JULHO 2026'!D341 -> 16047193 | B70: =COUNTIF('JULHO 2026'!D11:D599,'POR PACIENTE'!A342) -> 0
A71: ='JULHO 2026'!D347 -> 20744884 | B71: =COUNTIF('JULHO 2026'!D11:D599,'POR PACIENTE'!A348) -> 0
A72: ='JULHO 2026'!D353 -> 20563540 | B72: =COUNTIF('JULHO 2026'!D11:D599,'POR PACIENTE'!A354) -> 0
A73: ='JULHO 2026'!D359 -> 17922378 | B73: =COUNTIF('JULHO 2026'!D11:D599,'POR PACIENTE'!A360) -> 0
A74: ='JULHO 2026'!D365 -> 20687075 | B74: =COUNTIF('JULHO 2026'!D11:D599,'POR PACIENTE'!A366) -> 0
A75: ='JULHO 2026'!D371 -> 5599170 | B75: =COUNTIF('JULHO 2026'!D11:D599,'POR PACIENTE'!A372) -> 0
A76: ='JULHO 2026'!D377 -> 20632477 | B76: =COUNTIF('JULHO 2026'!D11:D599,'POR PACIENTE'!A378) -> 0
A77: ='JULHO 2026'!D383 -> 3999877 | B77: =COUNTIF('JULHO 2026'!D11:D599,'POR PACIENTE'!A384) -> 0
A78: ='JULHO 2026'!D389 -> 20389938 | B78: =COUNTIF('JULHO 2026'!D11:D599,'POR PACIENTE'!A390) -> 0
A79: ='JULHO 2026'!D395 -> 20731022 | B79: =COUNTIF('JULHO 2026'!D11:D599,'POR PACIENTE'!A396) -> 0
A80: ='JULHO 2026'!D401 -> 20417739 | B80: =COUNTIF('JULHO 2026'!D11:D599,'POR PACIENTE'!A402) -> 0
A81: ='JULHO 2026'!D407 -> 10106599 | B81: =COUNTIF('JULHO 2026'!D11:D599,'POR PACIENTE'!A408) -> 0
A82: ='JULHO 2026'!D413 -> 9525684 | B82: =COUNTIF('JULHO 2026'!D11:D599,'POR PACIENTE'!A414) -> 0
A83: ='JULHO 2026'!D419 -> 20754685 | B83: =COUNTIF('JULHO 2026'!D11:D599,'POR PACIENTE'!A420) -> 0
A84: ='JULHO 2026'!D425 -> 13679378 | B84: =COUNTIF('JULHO 2026'!D11:D599,'POR PACIENTE'!A426) -> 0
A85: ='JULHO 2026'!D431 -> 20288270 | B85: =COUNTIF('JULHO 2026'!D11:D599,'POR PACIENTE'!A432) -> 0
A86: ='JULHO 2026'!D437 -> 20316758 | B86: =COUNTIF('JULHO 2026'!D11:D599,'POR PACIENTE'!A438) -> 0
A87: ='JULHO 2026'!D443 -> 20437646 | B87: =COUNTIF('JULHO 2026'!D11:D599,'POR PACIENTE'!A444) -> 0
A88: ='JULHO 2026'!D449 -> 10466159 | B88: =COUNTIF('JULHO 2026'!D11:D599,'POR PACIENTE'!A450) -> 0
A89: ='JULHO 2026'!D455 -> 20378766 | B89: =COUNTIF('JULHO 2026'!D11:D599,'POR PACIENTE'!A456) -> 0
A90: ='JULHO 2026'!D461 -> 20555033 | B90: =COUNTIF('JULHO 2026'!D11:D599,'POR PACIENTE'!A462) -> 0
A91: ='JULHO 2026'!D467 -> 6004071 | B91: =COUNTIF('JULHO 2026'!D11:D599,'POR PACIENTE'!A468) -> 0
A92: ='JULHO 2026'!D473 -> 20052775 | B92: =COUNTIF('JULHO 2026'!D11:D599,'POR PACIENTE'!A474) -> 0
A93: ='JULHO 2026'!D479 -> 20390290 | B93: =COUNTIF('JULHO 2026'!D11:D599,'POR PACIENTE'!A480) -> 0
A94: ='JULHO 2026'!D485 -> 20424636 | B94: =COUNTIF('JULHO 2026'!D11:D599,'POR PACIENTE'!A486) -> 0
A95: ='JULHO 2026'!D491 -> 20302022 | B95: =COUNTIF('JULHO 2026'!D11:D599,'POR PACIENTE'!A492) -> 0
A96: ='JULHO 2026'!D497 -> 20398822 | B96: =COUNTIF('JULHO 2026'!D11:D599,'POR PACIENTE'!A498) -> 0
A97: ='JULHO 2026'!D503 -> 14749915 | B97: =COUNTIF('JULHO 2026'!D11:D599,'POR PACIENTE'!A504) -> 0
A98: ='JULHO 2026'!D509 -> 15105216 | B98: =COUNTIF('JULHO 2026'!D11:D599,'POR PACIENTE'!A510) -> 0
A99: PACIENTE | B99: frequencia mensal | C99: Valor pago
A100: ='JULHO 2026'!D515 -> 20355533 | B100: =COUNTIF('JULHO 2026'!D11:D599,'POR PACIENTE'!A516) -> 0
A101: ='JULHO 2026'!D521 | B101: =COUNTIF('JULHO 2026'!D11:D599,'POR PACIENTE'!A522) -> 0
A102: ='JULHO 2026'!#REF! -> #ERROR! | B102: =COUNTIF('JULHO 2026'!D11:D599,'POR PACIENTE'!A528) -> 0
A103: ='JULHO 2026'!#REF! -> #ERROR! | B103: =COUNTIF('JULHO 2026'!D11:D599,'POR PACIENTE'!A534) -> 0
A104: ='JULHO 2026'!#REF! -> #ERROR! | B104: =COUNTIF('JULHO 2026'!D11:D599,'POR PACIENTE'!A540) -> 0
A105: ='JULHO 2026'!#REF! -> #ERROR! | B105: =COUNTIF('JULHO 2026'!D11:D599,'POR PACIENTE'!A546) -> 0
...

Sheet Planilha5

Sheet Planilha6

Sheet Planilha7

Sheet Planilha4

Sheet Plan2
B1: GOVERNO DO ESTADO DA BAHIA
B2: Secretaria da Saúde do Estado da Bahia – SESAB
B3: Hospital Geral Clériston Andrade - HGCA
D5: Feira de Santana, 21 MARÇO de 2024.
A6: De: Contas Hospitalares
A7: Para: Diretoria Médica/ Coordenação Neurologia
A8: Relatório de pacientes que realizaram neurocirurgia no HGCA em MARÇO 2024
A11: Nº | B11: Nome | C11: Data da cirurgia | D11: Número de registro | E11: OBSERVAÇÃO
A12: ='JULHO 2026'!A143 -> 23 | B12: ='JULHO 2026'!B143 -> IG ANGELO EMANUEL SAMPAIO | C12: ='JULHO 2026'!C143 -> 46214 | D12: ='JULHO 2026'!D143 -> 20405965 | E12: regular para lançar na fatura de março pois IH com da data 01/03/2024
A14: ='JULHO 2026'!A161 -> 26 | B14: ='JULHO 2026'!B161 -> MARIA FRANCO SANTA BARBARA | C14: ='JULHO 2026'!C161 -> 46213 | D14: ='JULHO 2026'!D161 -> 20385191 | E14: já lançado e cobrado na fatura de fevereiro n°41
A15: ='JULHO 2026'!A167 -> 27 | B15: ='JULHO 2026'!B167 -> LEONICE ESTEVA DE CERQUEIRA DE JESUS | C15: ='JULHO 2026'!C167 -> 46214 | D15: ='JULHO 2026'!D167 -> 20405734 | E15: já lançado e cobrado na fatura de fevereiro n°42
A16: ='JULHO 2026'!A173 -> 28 | B16: ='JULHO 2026'!B173 -> EMMANUEL BRITO DE OLIVEIRA | C16: ='JULHO 2026'!C173 -> 46216 | D16: ='JULHO 2026'!D173 -> 20316758 | E16: já lançado e cobrado na fatura de fevereiro n°45
A17: ='JULHO 2026'!A179 -> 29 | B17: ='JULHO 2026'!B179 -> VENCELENCIO PEREIRA MASCARENHAS | C17: ='JULHO 2026'!C179 -> 46216 | D17: ='JULHO 2026'!D179 -> 20441002
A18: ='JULHO 2026'!A185 -> 30 | B18: ='JULHO 2026'!B185 -> ANISIO DANTAS COELHO | C18: ='JULHO 2026'!C185 -> 46211 | D18: ='JULHO 2026'!D185 -> 20118261 | E18: já lançado e cobrado na fatura de fevereiro n°44
A19: ='JULHO 2026'!A191 -> 31 | B19: ='JULHO 2026'!B191 -> ELINEUZA CERQUEIRA DA SILVA | C19: ='JULHO 2026'!C191 -> 46212 | D19: ='JULHO 2026'!D191 -> 20398822 | E19: já lançado e cobrado na fatura de fevereiro n°43
A20: ='JULHO 2026'!A197 -> 32 | B20: ='JULHO 2026'!B197 -> ZACARIAS ANDRADE DA SILVA | C20: ='JULHO 2026'!C197 -> 46214 | D20: ='JULHO 2026'!D197 -> 20426466 | E20: já lançado e cobrado na fatura de fevereiro n°46
A21: ='JULHO 2026'!A209 -> 34 | B21: ='JULHO 2026'!B209 -> EDINEY DE ARAUJO SOUZA | C21: ='JULHO 2026'!C209 -> 46220 | D21: ='JULHO 2026'!D209 -> 20530143 | E21: já lançado e cobrado na fatura de fevereiro n°57
A23: ='JULHO 2026'!A215 -> 35 | B23: ='JULHO 2026'!B215 -> LUIZ FELIPE DOS SANTOS BRITTO | C23: ='JULHO 2026'!C215 -> 46218 | D23: ='JULHO 2026'!D215 -> 20186698 | E23: já lançado e cobrado na fatura de janeiro n°19
A24: ='JULHO 2026'!A221 -> 36 | B24: ='JULHO 2026'!B221 -> ODAIR JOSE CERQUEIRA OLIVEIRA | C24: ='JULHO 2026'!C221 -> 46223 | D24: ='JULHO 2026'!D221 -> 20424636
A25: =A17 -> 29 | B25: =B17 -> VENCELENCIO PEREIRA MASCARENHAS | C25: =C17 -> 46216 | D25: =D17 -> 20441002 | E25: já lançado e cobrado na fatura de janeiro n°84
A27: =A24 -> 36 | B27: =B24 -> ODAIR JOSE CERQUEIRA OLIVEIRA | C27: =C24 -> 46223 | D27: =D24 -> 20424636 | E27: paciente da VASCULAR

Sheet Plan1
A10: MARIA SÃO PEDRO PERERIA DA CRUZ | B10: 45331 | C10: 7762818
A16: LUCIANA DE JESUS RIBEIRO | B16: 45331 | C16: 7762750
A22: IRACY SANTOS SILVA | B22: 45331 | C22: 6443295
A28: IRACY DA CRUZ SOUZA | B28: 45331 | C28: 7762776
A34: LETYCIA KEVELLYN DA SILVA SANTOS | B34: 45331 | C34: 7828932
A40: ALESANDRA GONÇALVES DE OLIVEIRA RIOS | B40: 45331 | C40: 5257415
A46: ADMARIO AMORIM DA SILVA | B46: 45331 | C46: 7762727
A52: NILZA AMORIM AQUINO | B52: 45331 | C52: 7762552
A61: =9513.6+29704.76 -> 39218.36

Sheet Plan4
B1: GOVERNO DO ESTADO DA BAHIA
B2: Secretaria da Saúde do Estado da Bahia – SESAB
B3: Hospital Geral Clériston Andrade - HGCA
D5: Feira de Santana, 07 ABRIL de 2024.
A6: De: Contas Hospitalares
A7: Para: Diretoria Médica/ Coordenação Neurologia
A8: Relatório de pacientes que realizaram neurocirurgia no HGCA em MARÇO 2024
A11: Nº | B11: Nome | C11: Data da cirurgia | D11: Número de registro | E11: OBSERVAÇÃO | F11: MEDICO
B14: BISPO MOREIRA DA SILVA | C14: 45372 | D14: 7778368 | E14: SEM DOSSIÊ | F14: EDUARDO VARJÃO
B15: JAIME DE JESUS SILVA | C15: 45374 | D15: 8287229 | E15: SEM DOSSIÊ | F15: ALLAN FRANÇA
B16: ANA RITA LOPES DE OLIVEIRA FONSECA | C16: 45376 | D16: 4439972 | E16: SEM DOSSIÊ | F16: DOUGLAS TRAVASSOS

Sheet Plan3
P24: 4 | R24: 12
P25: 2 | R25: 4
P26: 4 | R26: 5
P27: 2 | R27: 16
P28: =SUM(P24:P27) -> 12 | R28: 4
R29: =SUM(R24:R28) -> 41

Sheet Plan5
B1: GOVERNO DO ESTADO DA BAHIA
B2: Secretaria da Saúde do Estado da Bahia – SESAB
B3: Hospital Geral Clériston Andrade - HGCA
D5: Feira de Santana, 07 ABRIL de 2024.
A6: De: Contas Hospitalares
A7: Para: Diretoria Médica/ Coordenação Neurologia
A8: Relatório de pacientes que realizaram neurocirurgia no HGCA em MARÇO 2024
A11: Nº | B11: Nome | C11: Data da cirurgia | D11: Número de registro | E11: OBSERVAÇÃO | F11: MEDICO
B14: BERNARDINO JOSE DOSA SANTOS NETO | C14: 45353 | D14: 7999287 | E14: ANTONIO GUTEMBERG | F14: DOUGLAS TRAVASSOS
B15: ARNALDO NUNES | C15: 45357 | D15: 7923600 | E15: CAMILA MOURA | F15: JAQUISSON GUIMARÃES
B16: IG CRISTIANO DE JESUS SILVA | C16: 45382 | D16: 8347171 | E16: 45381 | F16: EDUARDO VARJÃO
B17: BRUNO DOS SANTOS PAZ | C17: 45355 | D17: 8007437 | E17: AUSENTE NA FATURA NEURO | F17: CAMILA MOURA
B18: AILTON SOUZA DE ALMEIDA | C18: 45360 | D18: 785115 | E18: AUSENTE NA FATURA NEURO | F18: WAGNER HERCULANO
B19: MARIA HELENA DE JESUS | C19: 45360 | D19: 7772700 | E19: AUSENTE NA FATURA NEURO | F19: DOUGLAS TRAVASSOS
B20: JORGE MIRANDA DE ARAUJO | C20: 29/02/2024 para 01/03/2024 | D20: 7996119 | E20: AUSENTE NA FATURA NEURO | F20: EDUARDO VARJÃO
B21: MAIARA CAMILO DE OLIVEIRA | C21: 19/03/20024 | D21: 6857809 | E21: AUSENTE NA FATURA NEURO | F21: DOUGLAS TRAVASSOS
B22: RENAN DOS SANTOS SOARES | C22: 45365 | D22: 6710529 | E22: AUSENTE NA FATURA NEURO | F22: EDUARDO VARJÃO

Sheet Plan6

Sheet Planilha15
M33: 9
M34: 9
M35: 10
M36: 10
M37: 9
M38: 8
M39: 9
M40: 11
M41: 4

Sheet Plan7
A3: 12 | B3: EDIMAR SIMOES DOS SANTOS | C3: 45618 | D3: 10748739 | H3: ='0403030'!A14 -> 040303002-1 | I3: eduardo | K3: OPME
B7: RECEBIDO EM 06/12/2024
B8: DEVOLVIDO EM 09/12/2024
A10: 1 | B10: ='JULHO 2026'!B11 -> CARMELITA MARIA DE JESUS | C10: ='JULHO 2026'!C11 -> 46205 | D10: ='JULHO 2026'!D11 -> 19999507 | E10: ='JULHO 2026'!E11 -> 0408030291 | F10: ='JULHO 2026'!F11 -> artrodese toraco-lombo-sacra posterior 2 niveis | G10: ='JULHO 2026'!G11 -> 1155.78 | H10: ='JULHO 2026'!H11 -> EDUARDO VARJÃO VIEIRA | I10: C/OPME
A11: 2 | B11: ='JULHO 2026'!B17 -> JAILSON DE JESUS NUNES | C11: ='JULHO 2026'!C17 -> 46205 | D11: ='JULHO 2026'!D17 -> 20170007 | E11: ='JULHO 2026'!E17 -> 0408030917 | F11: ='JULHO 2026'!F17 -> artrodese cervical /cervico toráxica posterior 4 niveis | G11: ='JULHO 2026'!G17 -> 1155.78 | H11: ='JULHO 2026'!H17 -> WAGNER DE AZEVEDO HERCULANO | I11: C/OPME
A12: 3 | B12: ='JULHO 2026'!B23 -> MOISANE DE OLIVERIA COSTA | C12: ='JULHO 2026'!C23 -> 46205 | D12: ='JULHO 2026'!D23 -> 18270306 | E12: ='JULHO 2026'!E23 -> 0403010101 | F12: ='JULHO 2026'!F23 -> derivação ventricular para peritoneo/atrio/pleura/raque | G12: ='JULHO 2026'!G23 -> 682.08 | H12: ='JULHO 2026'!H23 -> WAGNER DE AZEVEDO HERCULANO | I12: C/OPME
A13: 4 | B13: ='JULHO 2026'!B29 -> ALBERTO CASTRO DOS SANTOS | C13: ='JULHO 2026'!C29 -> 46205 | D13: ='JULHO 2026'!D29 -> 16019804 | E13: ='JULHO 2026'!E29 -> 0403010314 | F13: ='JULHO 2026'!F29 -> Tratamento cirurgico de hematoma subdural cronico | G13: ='JULHO 2026'!G29 -> 682.08 | H13: ='JULHO 2026'!H29 -> EDUARDO VARJÃO VIEIRA | I13: C/OPME
A14: 5 | B14: ='JULHO 2026'!B35 -> JOSE HENRIQUE COSTA SOUZA | C14: ='JULHO 2026'!C35 -> 46205 | D14: ='JULHO 2026'!D35 -> 20207494 | E14: ='JULHO 2026'!E35 -> 0403010241 | F14: ='JULHO 2026'!F35 -> tratamento cirurgico de fistula liquorica craniana | G14: ='JULHO 2026'!G35 -> 671.94 | H14: ='JULHO 2026'!H35 -> EDUARDO VARJÃO VIEIRA | I14: S/OPME
A15: 6 | B15: ='JULHO 2026'!B41 -> GIZELA SANTOS AMPAIO | C15: ='JULHO 2026'!C41 -> 46205 | D15: ='JULHO 2026'!D41 -> 20207510 | E15: ='JULHO 2026'!E41 -> 0403010187 | F15: ='JULHO 2026'!F41 -> revisão derivação ventricular para peritoneo/atrio/pleura/raque | G15: ='JULHO 2026'!G41 -> 572 | H15: ='JULHO 2026'!H41 -> JAQUISSON DE DEUS GUIMARÃES FILHO | I15: C/OPME
A16: 7 | B16: ='JULHO 2026'!#REF! -> #ERROR! | C16: ='JULHO 2026'!C47 -> 46206 | D16: ='JULHO 2026'!D47 -> 19937804 | E16: ='JULHO 2026'!E47 -> 0408030267 | F16: ='JULHO 2026'!F47 -> artrodese toraco-lombo-sacra posterior 1 nivel | G16: ='JULHO 2026'!G47 -> 470 | H16: ='JULHO 2026'!H47 -> WAGNER DE AZEVEDO HERCULANO | I16: C/OPME
A17: 8 | B17: ='JULHO 2026'!B53 -> JUCINEIDE DOS SANTOS SILVA | C17: ='JULHO 2026'!C53 -> 46205 | D17: ='JULHO 2026'!D53 -> 14123228 | E17: ='JULHO 2026'!E53 -> 0403030099 | F17: ='JULHO 2026'!F53 -> microcirurgia de tumor medular técnica complementar | G17: ='JULHO 2026'!G53 -> 1540.56 | H17: ='JULHO 2026'!#REF! -> #ERROR! | I17: C/OPME
A18: 9 | B18: ='JULHO 2026'!B59 -> JOSE BISPO | C18: ='JULHO 2026'!C59 -> 46204 | D18: ='JULHO 2026'!D59 -> 20051595 | E18: ='JULHO 2026'!E59 -> 0408030100 | F18: ='JULHO 2026'!F59 -> artrodese cervical anterior 4 niveis | G18: ='JULHO 2026'!G59 -> 1155.78 | H18: ='JULHO 2026'!H59 -> ARTUR BASTOS ROCHA | I18: S/OPME
A19: 10 | B19: ='JULHO 2026'!B65 -> GERSON DOS SANTOS BASTOS | C19: ='JULHO 2026'!C65 -> 46204 | D19: ='JULHO 2026'!D65 -> 20166112 | E19: ='JULHO 2026'!E65 -> 0403010195 | F19: ='JULHO 2026'!F65 -> tratamento cirurgico de abcesso intracraniano | G19: ='JULHO 2026'!G65 -> 559.95 | H19: ='JULHO 2026'!H65 -> EDUARDO VARJÃO VIEIRA | I19: S/OPME
A20: 11 | B20: ='JULHO 2026'!B71 -> DILMARCI BRANDÃO DE OLIVEIRA | C20: ='JULHO 2026'!C71 -> 46572 | D20: ='JULHO 2026'!D71 -> 15673171 | E20: ='JULHO 2026'!E71 -> 0403020018 | F20: ='JULHO 2026'!F71 -> enxerto microcirurgico de nervo periferico ( 2 ou mais nervos) | G20: ='JULHO 2026'!G71 -> 500.5 | H20: ='JULHO 2026'!H71 -> PEDRO HENRIQUE V. PONDÉ DE SENA | I20: C/OPME
A21: 12 | B21: ='JULHO 2026'!B77 -> SILVIO PEREIRA GOMES | C21: ='JULHO 2026'!C77 -> 46206 | D21: ='JULHO 2026'!D77 -> 10477966 | E21: ='JULHO 2026'!E77 -> 0303040041 | F21: ='JULHO 2026'!F77 -> Tratamento Clinico de Abscesso Cerebral | G21: ='JULHO 2026'!G77 -> 84.36 | H21: ='JULHO 2026'!H77 -> WAGNER DE AZEVEDO HERCULANO | I21: C/OPME
B22: não consta na lita de pendencias do mês
B23: de novembro
B29: RECEBIDO EM 11/12/2024
B30: DEVOLVIDO EM 12/12/2024
A32: 1 | B32: ='JULHO 2026'!B77 -> SILVIO PEREIRA GOMES | C32: ='JULHO 2026'!C77 -> 46206 | D32: ='JULHO 2026'!D77 -> 10477966 | E32: ='JULHO 2026'!E77 -> 0303040041 | F32: ='JULHO 2026'!F77 -> Tratamento Clinico de Abscesso Cerebral | G32: ='JULHO 2026'!G77 -> 84.36 | H32: ='JULHO 2026'!H77 -> WAGNER DE AZEVEDO HERCULANO | I32: C/OPME
A33: 2 | B33: ='JULHO 2026'!B83 -> JOSEILDA LIRA DA SILVA | C33: ='JULHO 2026'!C83 -> 46208 | D33: ='JULHO 2026'!D83 -> 10274421 | E33: ='JULHO 2026'!E83 -> 0403030129 | F33: ='JULHO 2026'!F83 -> microcirurgia de tumor de base do cranio | G33: ='JULHO 2026'!G83 -> 1865.92 | H33: ='JULHO 2026'!H83 -> WAGNER DE AZEVEDO HERCULANO | I33: C/OPME
A34: 3 | B34: ='JULHO 2026'!B89 -> IG JOSE KLEBIO DE ALMEIDA SOUZA | C34: ='JULHO 2026'!C89 -> 46209 | D34: ='JULHO 2026'!D89 -> 20319273 | E34: ='JULHO 2026'!E89 -> 0403010241 | F34: ='JULHO 2026'!F89 -> tratamento cirurgico de fistula liquorica craniana | G34: ='JULHO 2026'!G89 -> 671.94 | H34: ='JULHO 2026'!H89 -> CAMILA MOURA DE SOUSA | I34: C/OPME
A35: 4 | B35: ='JULHO 2026'!B95 -> MARICLEIDE LINARD DE LIMA DE PAULA | C35: ='JULHO 2026'!C95 -> 46211 | D35: ='JULHO 2026'!D95 -> 20275442 | E35: ='JULHO 2026'!E95 -> 0403040116 | F35: ='JULHO 2026'!F95 -> microcirurgia para aneurisma da circulaço cerebral anterior menor que 1,5 cm | G35: ='JULHO 2026'!G95 -> 1568 | H35: ='JULHO 2026'!H95 -> JAQUISSON DE DEUS GUIMARÃES FILHO | I35: C/OPME
A36: 5 | B36: ='JULHO 2026'!B101 -> VALDIREI DIAS DA ROCHA | C36: ='JULHO 2026'!C101 -> 46212 | D36: ='JULHO 2026'!D101 -> 4234761 | E36: ='JULHO 2026'!E101 -> 0408030267 | F36: ='JULHO 2026'!F101 -> artrodese toraco-lombo-sacra posterior 1 nivel | G36: ='JULHO 2026'!G101 -> 470 | H36: ='JULHO 2026'!H101 -> WAGNER DE AZEVEDO HERCULANO | I36: C/OPME
A37: 6 | B37: ='JULHO 2026'!B107 -> ANDRADE DE NOVAIS SANTOS | C37: ='JULHO 2026'!C107 -> 46207 | D37: ='JULHO 2026'!D107 -> 29297966 | E37: ='JULHO 2026'!E107 -> 0408030054 | F37: ='JULHO 2026'!F107 -> artrodese cervical /cervico toráxica posterior 3 niveis | G37: ='JULHO 2026'!G107 -> 1155.78 | H37: ='JULHO 2026'!H107 -> ARTUR BASTOS ROCHA | I37: C/OPME
A38: 7 | B38: ='JULHO 2026'!B113 -> ANTONIO SIMOES DA CONCEIÇÃO | C38: ='JULHO 2026'!C113 -> 46211 | D38: ='JULHO 2026'!D113 -> 20329637 | E38: ='JULHO 2026'!E113 -> 0403010314 | F38: ='JULHO 2026'!F113 -> Tratamento cirurgico de hematoma subdural cronico | G38: ='JULHO 2026'!G113 -> 682.08 | H38: ='JULHO 2026'!H113 -> ARTUR BASTOS ROCHA | I38: C/OPME
A39: 8 | B39: ='JULHO 2026'!B119 -> RAIMUNDO DOS SANTOS MORAES | C39: ='JULHO 2026'!C119 -> 46209 | D39: ='JULHO 2026'!D119 -> 20313573 | E39: ='JULHO 2026'!E119 -> 0403010012 | F39: ='JULHO 2026'!F119 -> Cranioplastia | G39: ='JULHO 2026'!G119 -> 522.48 | H39: ='JULHO 2026'!H119 -> CAMILA MOURA DE SOUSA | I39: S/OPME
A40: 9 | B40: ='JULHO 2026'!B125 -> WELLINGTON ALVES DA SILVA | C40: ='JULHO 2026'!C125 -> 46210 | D40: ='JULHO 2026'!D125 -> 20338463 | E40: ='JULHO 2026'!E125 -> 0403010110 | F40: ='JULHO 2026'!F125 -> descompressão de orbita por doença ou trauma | G40: ='JULHO 2026'!G125 -> 786.5 | H40: ='JULHO 2026'!H125 -> PEDRO HENRIQUE V. PONDÉ DE SENA | I40: C/OPME
A41: 10 | B41: ='JULHO 2026'!B131 -> CICERO PEDRO DA SILVA | C41: ='JULHO 2026'!C131 -> 46207 | D41: ='JULHO 2026'!D131 -> 18069914 | E41: ='JULHO 2026'!E131 -> 0408030291 | F41: ='JULHO 2026'!F131 -> artrodese toraco-lombo-sacra posterior 2 niveis | G41: ='JULHO 2026'!G131 -> 1155.78 | H41: ='JULHO 2026'!H131 -> WAGNER DE AZEVEDO HERCULANO | I41: C/OPME
A42: 11 | B42: ='JULHO 2026'!B137 -> EMILY MARLENE MACHADO | C42: ='JULHO 2026'!C137 -> 46215 | D42: ='JULHO 2026'!D137 -> 20428447 | E42: ='JULHO 2026'!E137 -> 0408030275 | F42: ='JULHO 2026'!F137 -> artrodese toraco-lombo-sacra posterior 3 niveis | G42: ='JULHO 2026'!G137 -> 1155.78 | H42: ='JULHO 2026'!H137 -> ARTUR BASTOS ROCHA | I42: S/OPME
B45: RECEBIDO EM 19/12/2024
B46: DEVOLVIDO EM 20/12/2024
A48: 1 | B48: ='JULHO 2026'!B143 -> IG ANGELO EMANUEL SAMPAIO | C48: ='JULHO 2026'!C143 -> 46214 | D48: ='JULHO 2026'!D143 -> 20405965 | E48: ='JULHO 2026'!E143 -> 0403040078 | F48: ='JULHO 2026'!F143 -> microcirurgia vascular intracraniana (com tecnica complementar) | G48: ='JULHO 2026'!G143 -> 1865.92 | H48: ='JULHO 2026'!H143 -> IOGO HENRIQUE DE O. ARAUJO | I48: S/OPME
A49: 2 | B49: ='JULHO 2026'!B149 -> MARIA EUZEBIA DA COSTA | C49: ='JULHO 2026'!C149 -> 46214 | D49: ='JULHO 2026'!D149 -> 19892868 | E49: ='JULHO 2026'!E149 -> 0403030129 | F49: ='JULHO 2026'!F149 -> microcirurgia de tumor de base do cranio | G49: ='JULHO 2026'!G149 -> 1865.92 | H49: ='JULHO 2026'!H149 -> IOGO HENRIQUE DE O. ARAUJO | I49: S/OPME
A50: 3 | B50: ='JULHO 2026'!B155 -> JOSE FERREIRA DA SILVA | C50: ='JULHO 2026'!C155 -> 46207 | D50: ='JULHO 2026'!D155 -> 20261186 | E50: ='JULHO 2026'!E155 -> 0403010241 | F50: ='JULHO 2026'!F155 -> tratamento cirurgico de fistula liquorica craniana | G50: ='JULHO 2026'!G155 -> 671.94 | H50: ='JULHO 2026'!H155 -> PEDRO HENRIQUE V. PONDÉ DE SENA | I50: S/OPME
A51: 4 | B51: ='JULHO 2026'!B161 -> MARIA FRANCO SANTA BARBARA | C51: ='JULHO 2026'!C161 -> 46213 | D51: ='JULHO 2026'!D161 -> 20385191 | E51: ='JULHO 2026'!E161 -> 0403010314 | F51: ='JULHO 2026'!F161 -> Tratamento cirurgico de hematoma subdural cronico | G51: ='JULHO 2026'!G161 -> 682.08 | H51: ='JULHO 2026'!H161 -> ARTUR BASTOS ROCHA | I51: S/OPME
A52: 5 | B52: ='JULHO 2026'!B167 -> LEONICE ESTEVA DE CERQUEIRA DE JESUS | C52: ='JULHO 2026'!C167 -> 46214 | D52: ='JULHO 2026'!D167 -> 20405734 | E52: ='JULHO 2026'!E167 -> 0403010314 | F52: ='JULHO 2026'!F167 -> Tratamento cirurgico de hematoma subdural cronico | G52: ='JULHO 2026'!G167 -> 682.08 | H52: ='JULHO 2026'!H167 -> ARTUR BASTOS ROCHA | I52: S/OPME
A53: 6 | B53: ='JULHO 2026'!B173 -> EMMANUEL BRITO DE OLIVEIRA | C53: ='JULHO 2026'!C173 -> 46216 | D53: ='JULHO 2026'!D173 -> 20316758 | E53: ='JULHO 2026'!E173 -> 0408030623 | F53: ='JULHO 2026'!F173 -> revisão de artrodese / tratamento cirurgico de pseudoartrose da coluna cervical posterior | G53: ='JULHO 2026'!G173 -> 770.99 | H53: ='JULHO 2026'!H173 -> WAGNER DE AZEVEDO HERCULANO | I53: S/OPME
A54: 7 | B54: ='JULHO 2026'!B179 -> VENCELENCIO PEREIRA MASCARENHAS | C54: ='JULHO 2026'!C179 -> 46216 | D54: ='JULHO 2026'!D179 -> 20441002 | E54: ='JULHO 2026'!E179 -> 0403010241 | F54: ='JULHO 2026'!F179 -> tratamento cirurgico de fistula liquorica craniana | G54: ='JULHO 2026'!G179 -> 671.94 | H54: ='JULHO 2026'!H179 -> CAMILA MOURA DE SOUSA | I54: C/OPME
A55: 8 | B55: ='JULHO 2026'!B185 -> ANISIO DANTAS COELHO | C55: ='JULHO 2026'!C185 -> 46211 | D55: ='JULHO 2026'!D185 -> 20118261 | E55: ='JULHO 2026'!E185 -> 0403010047 | F55: ='JULHO 2026'!F185 -> Craniotomia para retirada de cisto/ abcesso/granuloma encefalico | G55: ='JULHO 2026'!G185 -> 671.94 | H55: ='JULHO 2026'!H185 -> CAMILA MOURA DE SOUSA | I55: C/OPME
A56: 9 | B56: ='JULHO 2026'!B191 -> ELINEUZA CERQUEIRA DA SILVA | C56: ='JULHO 2026'!C191 -> 46212 | D56: ='JULHO 2026'!D191 -> 20398822 | E56: ='JULHO 2026'!E191 -> 0403010101 | F56: ='JULHO 2026'!F191 -> derivação ventricular para peritoneo/atrio/pleura/raque | G56: ='JULHO 2026'!G191 -> 682.08 | H56: ='JULHO 2026'!H191 -> WAGNER DE AZEVEDO HERCULANO | I56: S/OPME
A57: 10 | B57: ='JULHO 2026'!B197 -> ZACARIAS ANDRADE DA SILVA | C57: ='JULHO 2026'!C197 -> 46214 | D57: ='JULHO 2026'!D197 -> 20426466 | E57: ='JULHO 2026'!E197 -> 0403010314 | F57: ='JULHO 2026'!F197 -> Tratamento cirurgico de hematoma subdural cronico | G57: ='JULHO 2026'!G197 -> 682.08 | H57: ='JULHO 2026'!H197 -> CAMILA MOURA DE SOUSA | I57: C/OPME
A58: 11 | B58: ='JULHO 2026'!B203 -> ANTONIO PINTO DE ALMEIDA | C58: ='JULHO 2026'!C203 -> 46215 | D58: ='JULHO 2026'!D203 -> 20416632 | E58: ='JULHO 2026'!E203 -> 0403010306 | F58: ='JULHO 2026'!F203 -> Tratamento cirurgico de hematoma subdural agudo | G58: ='JULHO 2026'!G203 -> 682.08 | H58: ='JULHO 2026'!H203 -> ARTUR BASTOS ROCHA | I58: C/OPME
A59: 12 | B59: ='JULHO 2026'!B209 -> EDINEY DE ARAUJO SOUZA | C59: ='JULHO 2026'!C209 -> 46220 | D59: ='JULHO 2026'!D209 -> 20530143 | E59: ='JULHO 2026'!E209 -> 0408030275 | F59: ='JULHO 2026'!F209 -> artrodese toraco-lombo-sacra posterior 3 niveis | G59: ='JULHO 2026'!G209 -> 1155.78 | H59: ='JULHO 2026'!H209 -> WAGNER DE AZEVEDO HERCULANO | I59: C/OPME
A60: 13 | B60: ='JULHO 2026'!B215 -> LUIZ FELIPE DOS SANTOS BRITTO | C60: ='JULHO 2026'!C215 -> 46218 | D60: ='JULHO 2026'!D215 -> 20186698 | E60: ='JULHO 2026'!E215 -> 0403020018 | F60: ='JULHO 2026'!F215 -> enxerto microcirurgico de nervo periferico ( 2 ou mais nervos) | G60: ='JULHO 2026'!G215 -> 500.5 | H60: ='JULHO 2026'!H215 -> PEDRO HENRIQUE V. PONDÉ DE SENA | I60: C/OPME
A61: 14 | B61: ='JULHO 2026'!B221 -> ODAIR JOSE CERQUEIRA OLIVEIRA | C61: ='JULHO 2026'!C221 -> 46223 | D61: ='JULHO 2026'!D221 -> 20424636 | E61: ='JULHO 2026'!E221 -> 0415040035 | F61: ='JULHO 2026'!F221 -> Debridamento de ulcera/ de tecidos desvitalizados | G61: ='JULHO 2026'!G221 | H61: ='JULHO 2026'!H221 -> EDUARDO VARJÃO VIEIRA | I61: S/OPME
A62: 15 | B62: ='JULHO 2026'!B227 -> PAULO CEZAR DE QUEIROZ | C62: ='JULHO 2026'!C227 -> 46215 | D62: ='JULHO 2026'!D227 -> 20324711 | E62: ='JULHO 2026'!E227 -> 0408030275 | F62: ='JULHO 2026'!F227 -> artrodese toraco-lombo-sacra posterior 3 niveis | G62: ='JULHO 2026'!G227 -> 1155.78 | H62: ='JULHO 2026'!H227 -> ARTUR BASTOS ROCHA | I62: S/OPME
A63: 16 | B63: ='JULHO 2026'!B233 -> ANGELINA CARVALHO DE OLIVEIRA | C63: ='JULHO 2026'!C233 -> 46228 | D63: ='JULHO 2026'!D233 -> 20665766 | E63: ='JULHO 2026'!E233 -> 0403030153 | F63: ='JULHO 2026'!F233 -> Microcirurgia para tumor intracraniano (com tecnica complementar) | G63: ='JULHO 2026'!G233 -> 2054.08 | H63: ='JULHO 2026'!H233 -> WAGNER DE AZEVEDO HERCULANO | I63: C/OPME
A64: 17 | B64: ='JULHO 2026'!B239 -> ANTONIO AUGUSTINHO CARNEIRO | C64: ='JULHO 2026'!C239 -> 46230 | D64: ='JULHO 2026'!D239 -> 20765954 | E64: ='JULHO 2026'!E239 -> 0403010241 | F64: ='JULHO 2026'!F239 -> tratamento cirurgico de fistula liquorica craniana | G64: ='JULHO 2026'!G239 -> 671.94 | H64: ='JULHO 2026'!H239 -> CAMILA MOURA DE SOUSA | I64: C/OPME
A65: 18 | B65: ='JULHO 2026'!B245 -> DENILZO ALMEIDA PEREIRA | C65: ='JULHO 2026'!C245 -> 46228 | D65: ='JULHO 2026'!D245 -> 20723219 | E65: ='JULHO 2026'!E245 -> 0403010241 | F65: ='JULHO 2026'!F245 -> tratamento cirurgico de fistula liquorica craniana | G65: ='JULHO 2026'!G245 -> 671.94 | H65: ='JULHO 2026'!H245 -> CAMILA MOURA DE SOUSA | I65: C/OPME
A66: 19 | B66: ='JULHO 2026'!B251 -> DENISE OLIVEIRA DE DE ASSIS | C66: ='JULHO 2026'!C251 -> 46224 | D66: ='JULHO 2026'!D251 -> 18965277 | E66: ='JULHO 2026'!E251 -> 0408030100 | F66: ='JULHO 2026'!F251 -> artrodese cervical anterior 4 niveis | G66: ='JULHO 2026'!G251 -> 1155.78 | H66: ='JULHO 2026'!H251 -> ARTUR BASTOS ROCHA | I66: C/OPME
A67: 20 | B67: ='JULHO 2026'!B257 -> DIOGO GOMES COSTA | C67: ='JULHO 2026'!C257 -> 46227 | D67: ='JULHO 2026'!D257 -> 14457824 | E67: ='JULHO 2026'!E257 -> 0403020077 | F67: ='JULHO 2026'!F257 -> neurolise não funcional de nervos perifericos | G67: ='JULHO 2026'!G257 -> 180.75 | H67: ='JULHO 2026'!H257 -> WAGNER DE AZEVEDO HERCULANO | I67: C/OPME
A68: 21 | B68: ='JULHO 2026'!B263 -> DOUGLAS MOREIRA DANTAS DA ISLVA | C68: ='JULHO 2026'!C263 -> 46227 | D68: ='JULHO 2026'!D263 -> 16987141 | E68: ='JULHO 2026'!E263 -> 0403030153 | F68: ='JULHO 2026'!F263 -> Microcirurgia para tumor intracraniano (com tecnica complementar) | G68: ='JULHO 2026'!G263 -> 2054.08 | H68: ='JULHO 2026'!H263 -> LUIZ AUGUSTO MEDRADO SOEIRO | I68: C/OPME
A69: 22 | B69: ='JULHO 2026'!B269 -> EDIJANE ROZA RIBEIRO | C69: ='JULHO 2026'!C269 -> 46229 | D69: ='JULHO 2026'!D269 -> 20417739 | E69: ='JULHO 2026'!E269 -> 0403010020 | F69: ='JULHO 2026'!F269 -> Craniotomia descompressiva | G69: ='JULHO 2026'!G269 -> 391.86 | H69: ='JULHO 2026'!H269 -> CAMILA MOURA DE SOUSA | I69: C/OPME
A70: 23 | B70: ='JULHO 2026'!B275 -> EDILSON EVANGELISTA FERREIRA DOS SANTOS | C70: ='JULHO 2026'!C275 -> 46228 | D70: ='JULHO 2026'!D275 -> 20599759 | E70: ='JULHO 2026'!E275 -> 0403010241 | F70: ='JULHO 2026'!F275 -> tratamento cirurgico de fistula liquorica craniana | G70: ='JULHO 2026'!G275 -> 671.94 | H70: ='JULHO 2026'!H275 -> CAMILA MOURA DE SOUSA | I70: S/OPME
A71: 24 | B71: ='JULHO 2026'!B281 -> FELIPE SILVA DOS SANTOS | C71: ='JULHO 2026'!C281 -> 46217 | D71: ='JULHO 2026'!D281 -> 20482220 | E71: ='JULHO 2026'!E281 -> 0403010241 | F71: ='JULHO 2026'!F281 -> tratamento cirurgico de fistula liquorica craniana | G71: ='JULHO 2026'!G281 -> 671.94 | H71: ='JULHO 2026'!H281 -> PEDRO HENRIQUE V. PONDÉ DE SENA | I71: C/OPME
A72: 25 | B72: ='JULHO 2026'!B287 -> GIVANILDO DE JESUS CARVALHO | C72: ='JULHO 2026'!C287 -> 46222 | D72: ='JULHO 2026'!D287 -> 16688154 | E72: ='JULHO 2026'!E287 -> 0403010110 | F72: ='JULHO 2026'!F287 -> descompressão de orbita por doença ou trauma | G72: ='JULHO 2026'!G287 -> 786.5 | H72: ='JULHO 2026'!H287 -> EDUARDO VARJÃO VIEIRA | I72: S/OPME
A73: 26 | B73: ='JULHO 2026'!B293 -> HONORINO SALES DA CONCEIÇÃO | C73: ='JULHO 2026'!C293 -> 46224 | D73: ='JULHO 2026'!D293 -> 9525684 | E73: ='JULHO 2026'!E293 -> 0403010136 | F73: ='JULHO 2026'!F293 -> microcirurgia da siringomielia | G73: ='JULHO 2026'!G293 -> 896.19 | H73: ='JULHO 2026'!H293 -> ARTUR BASTOS ROCHA | I73: C/OPME

Sheet Planilha3

Sheet Plan8
